[
  {
    "id": "11170",
    "name": "Вафлі 34 г Рошен Roshetto milk глазуровані молочно-шоколадною глазур'ю",
    "category": "Вафлі",
    "imageUrl": "https://src.zakaz.atbmarket.com/cache/photos/11420/catalog_list_11420.jpg",
    "oldPrice": "12.80",
    "newPrice": "8.70",
    "cardPrice": "--.--",
    "quantity": 0
  },
  {
    "id": "11169",
    "name": "Вафлі 34 г Рошен Roshetto dark глазуровані шоколадною глазур'ю",
    "category": "Вафлі",
    "imageUrl": "https://src.zakaz.atbmarket.com/cache/photos/11419/catalog_list_11419.jpg",
    "oldPrice": "12.80",
    "newPrice": "8.70",
    "cardPrice": "--.--",
    "quantity": 0
  },
  {
    "id": "32655",
    "name": "Вафлі 34 г Roshen Roshetto peanut глазуровані шоколадною глазур'ю м/уп",
    "category": "Вафлі",
    "imageUrl": "https://src.zakaz.atbmarket.com/cache/photos/66255/catalog_list_66255.jpg",
    "oldPrice": "12.80",
    "newPrice": "8.70",
    "cardPrice": "--.--",
    "quantity": 0
  },
  {
    "id": "9028",
    "name": "Морозиво 75г Розумний вибір Каштан ескімо з комб.складом сировини з какао в конд.глазурі",
    "category": "Морозиво",
    "imageUrl": "https://src.zakaz.atbmarket.com/cache/photos/95601/catalog_list_95601.jpg",
    "oldPrice": "14.90",
    "newPrice": "9.50",
    "cardPrice": "--.--",
    "quantity": 0
  },
  {
    "id": "9027",
    "name": "Морозиво 75г  Розумний вибір Каштан з комбінованим складом сировини в кондитерській глазур",
    "category": "Морозиво",
    "imageUrl": "https://src.zakaz.atbmarket.com/cache/photos/95599/catalog_list_95599.jpg",
    "oldPrice": "14.90",
    "newPrice": "9.50",
    "cardPrice": "--.--",
    "quantity": 0
  },
  {
    "id": "38793",
    "name": "Корм 85 г CLUB 4 PAWS Преміум З ІНДИЧКОЮ В ЖЕЛЕ повнораціонний консервований для дорослих котів м/уп",
    "category": "Корм",
    "imageUrl": "https://src.zakaz.atbmarket.com/cache/photos/83423/catalog_list_83423.jpg",
    "oldPrice": "16.80",
    "newPrice": "11.00",
    "cardPrice": "--.--",
    "quantity": 0
  },
  {
    "id": "38795",
    "name": "Корм 85 г CLUB 4 PAWS Преміум пауч з качкою в соусі м/уп",
    "category": "Корм",
    "imageUrl": "https://src.zakaz.atbmarket.com/cache/photos/83425/catalog_list_83425.jpg",
    "oldPrice": "16.80",
    "newPrice": "11.00",
    "cardPrice": "--.--",
    "quantity": 0
  },
  {
    "id": "26847",
    "name": "Желе фруктове 120 г Злагода Вишня з соком п/стакан",
    "category": "Молочні десерти",
    "imageUrl": "https://src.zakaz.atbmarket.com/cache/photos/37361/catalog_list_37361.jpg",
    "oldPrice": "19.90",
    "newPrice": "12.50",
    "cardPrice": "--.--",
    "quantity": 0
  },
  {
    "id": "26849",
    "name": "Желе фруктове 120 г Злагода Персик з соком п/стакан",
    "category": "Молочні десерти",
    "imageUrl": "https://src.zakaz.atbmarket.com/cache/photos/37363/catalog_list_37363.jpg",
    "oldPrice": "19.90",
    "newPrice": "12.50",
    "cardPrice": "--.--",
    "quantity": 0
  },
  {
    "id": "42271",
    "name": "Желе фруктове 120 г Злагода Апельсин з соком п/стакан",
    "category": "Молочні десерти",
    "imageUrl": "https://src.zakaz.atbmarket.com/cache/photos/94041/catalog_list_94041.jpg",
    "oldPrice": "19.90",
    "newPrice": "12.50",
    "cardPrice": "--.--",
    "quantity": 0
  },
  {
    "id": "29667",
    "name": "Корм 80 г CLUB 4 PAWS Преміум Повнорац-й консер-й корм для дор-х стерил-х котів з крол-м в желе м/уп",
    "category": "Корм",
    "imageUrl": "https://src.zakaz.atbmarket.com/cache/photos/54221/catalog_list_54221.jpg",
    "oldPrice": "19.40",
    "newPrice": "12.80",
    "cardPrice": "--.--",
    "quantity": 0
  },
  {
    "id": "4868",
    "name": "Холодний чай 0,5л Своя Лінія Чорний зі смаком Малина",
    "category": "Напої",
    "imageUrl": "https://src.zakaz.atbmarket.com/cache/photos/2957/catalog_list_2957.jpg",
    "oldPrice": "19.90",
    "newPrice": "13.90",
    "cardPrice": "--.--",
    "quantity": 0
  },
  {
    "id": "2955",
    "name": "Батончик 42г Nestle Lion",
    "category": "Батончики",
    "imageUrl": "https://src.zakaz.atbmarket.com/cache/photos/71043/catalog_list_71043.jpg",
    "oldPrice": "21.90",
    "newPrice": "14.90",
    "cardPrice": "--.--",
    "quantity": 0
  },
  {
    "id": "41457",
    "name": "Йогурт 170 г Злагода Малятко Полуниця від 9 місяців 2,8% д/пак",
    "category": "Дитяча молочна продукція",
    "imageUrl": "https://src.zakaz.atbmarket.com/cache/photos/91429/catalog_list_91429.jpg",
    "oldPrice": "22.90",
    "newPrice": "16.70",
    "cardPrice": "--.--",
    "quantity": 0
  },
  {
    "id": "35107",
    "name": "Йогурт 170 г Злагода Малятко Персик від 9 місяців 2,8% д/пак",
    "category": "Дитяча молочна продукція",
    "imageUrl": "https://src.zakaz.atbmarket.com/cache/photos/72597/catalog_list_72597.jpg",
    "oldPrice": "22.90",
    "newPrice": "16.70",
    "cardPrice": "--.--",
    "quantity": 0
  },
  {
    "id": "8037",
    "name": "Морозиво 100г Ласунка Стакан Великан з підварками абрикосова та вишнева",
    "category": "Морозиво",
    "imageUrl": "https://src.zakaz.atbmarket.com/cache/photos/91951/catalog_list_91951.jpg",
    "oldPrice": "35.50",
    "newPrice": "17.50",
    "cardPrice": "--.--",
    "quantity": 0
  },
  {
    "id": "8001",
    "name": "Морозиво 100г Ласунка Стакан Великан з какао та вареним згущеним молоком",
    "category": "Морозиво",
    "imageUrl": "https://src.zakaz.atbmarket.com/cache/photos/91949/catalog_list_91949.jpg",
    "oldPrice": "35.50",
    "newPrice": "17.50",
    "cardPrice": "--.--",
    "quantity": 0
  },
  {
    "id": "40435",
    "name": "Морозиво 75 г Каштан зі смаком \"кокос-мигдаль\" в білій кондитерській глазурі ескімо п/ет",
    "category": "Морозиво",
    "imageUrl": "https://src.zakaz.atbmarket.com/cache/photos/89073/catalog_list_89073.jpg",
    "oldPrice": "35.90",
    "newPrice": "17.90",
    "cardPrice": "--.--",
    "quantity": 0
  },
  {
    "id": "38779",
    "name": "Мило косметичне 140г Своя Лінія тверде з екстрактом орхідеї/перлин м/уп",
    "category": "Мило",
    "imageUrl": "https://src.zakaz.atbmarket.com/cache/photos/83409/catalog_list_83409.jpg",
    "oldPrice": "26.60",
    "newPrice": "18.50",
    "cardPrice": "--.--",
    "quantity": 0
  },
  {
    "id": "21293",
    "name": "Соус 180 г Оліс Солодкий чилі",
    "category": "Соуси, кетчупи",
    "imageUrl": "https://src.zakaz.atbmarket.com/cache/photos/33257/catalog_list_33257.jpg",
    "oldPrice": "31.60",
    "newPrice": "19.90",
    "cardPrice": "--.--",
    "quantity": 0
  },
  {
    "id": "40429",
    "name": "Морозиво 70 г Рудь \"Donut\" зі смаком \"ваніль-полуниця\" п/ет",
    "category": "Морозиво",
    "imageUrl": "https://src.zakaz.atbmarket.com/cache/photos/89067/catalog_list_89067.jpg",
    "oldPrice": "34.90",
    "newPrice": "19.90",
    "cardPrice": "--.--",
    "quantity": 0
  },
  {
    "id": "706",
    "name": "Вафлі 40г Nestle Kit Kat в молочному шоколаді",
    "category": "Батончики",
    "imageUrl": "https://src.zakaz.atbmarket.com/cache/photos/71041/catalog_list_71041.jpg",
    "oldPrice": "29.90",
    "newPrice": "20.50",
    "cardPrice": "--.--",
    "quantity": 0
  },
  {
    "id": "12338",
    "name": "Йогурт 200 г Злагода Абрикос-морква 2,8%",
    "category": "Дитяча молочна продукція",
    "imageUrl": "https://src.zakaz.atbmarket.com/cache/photos/13127/catalog_list_13127.jpg",
    "oldPrice": "29.40",
    "newPrice": "21.40",
    "cardPrice": "--.--",
    "quantity": 0
  },
  {
    "id": "29687",
    "name": "Йогурт 200 г Злагода Малина-чорна смородина-шипшина від 9 місяців 2,8% ск/бут",
    "category": "Дитяча молочна продукція",
    "imageUrl": "https://src.zakaz.atbmarket.com/cache/photos/52811/catalog_list_52811.jpg",
    "oldPrice": "29.40",
    "newPrice": "21.40",
    "cardPrice": "--.--",
    "quantity": 0
  },
  {
    "id": "29689",
    "name": "Йогурт 200 г Злагода Яблуко-Банан від 9 місяців 2,8% ск/бут",
    "category": "Дитяча молочна продукція",
    "imageUrl": "https://src.zakaz.atbmarket.com/cache/photos/52813/catalog_list_52813.jpg",
    "oldPrice": "29.40",
    "newPrice": "21.40",
    "cardPrice": "--.--",
    "quantity": 0
  },
  {
    "id": "11329",
    "name": "Морозиво 85 г Рудь Ескімо Чорниця - Ожина",
    "category": "Морозиво",
    "imageUrl": "https://src.zakaz.atbmarket.com/cache/photos/88947/catalog_list_88947.jpg",
    "oldPrice": "37.50",
    "newPrice": "21.50",
    "cardPrice": "--.--",
    "quantity": 0
  },
  {
    "id": "41527",
    "name": "Пивo 0,5 л Beermix кавун  ж/б",
    "category": "Пиво",
    "imageUrl": "https://src.zakaz.atbmarket.com/cache/photos/91499/catalog_list_91499.jpg",
    "oldPrice": "37.90",
    "newPrice": "21.60",
    "cardPrice": "--.--",
    "quantity": 0
  },
  {
    "id": "105",
    "name": "Пиво 0,5л Оболонь BeerMix Лимон",
    "category": "Пиво",
    "imageUrl": "https://src.zakaz.atbmarket.com/cache/photos/28507/catalog_list_28507.jpg",
    "oldPrice": "37.90",
    "newPrice": "21.60",
    "cardPrice": "--.--",
    "quantity": 0
  },
  {
    "id": "27107",
    "name": "Квас 1 л Квaс Стapoкиївський живoгo бpoдіння бeзaлкoгoльний ПЕТ",
    "category": "Квас",
    "imageUrl": "https://src.zakaz.atbmarket.com/cache/photos/88955/catalog_list_88955.jpg",
    "oldPrice": "32.90",
    "newPrice": "21.70",
    "cardPrice": "--.--",
    "quantity": 0
  },
  {
    "id": "8372",
    "name": "Морозиво 85 г Ласунка Стоп-наркотик ескімо крем-брюле з маком у глазурі",
    "category": "Морозиво",
    "imageUrl": "https://src.zakaz.atbmarket.com/cache/photos/7500/catalog_list_7500.jpg",
    "oldPrice": "40.90",
    "newPrice": "21.90",
    "cardPrice": "--.--",
    "quantity": 0
  },
  {
    "id": "27355",
    "name": "Грінки житньо-пшеничні 100 г Flint Craft Grenki зі смаком Часник м/уп",
    "category": "Снеки",
    "imageUrl": "https://src.zakaz.atbmarket.com/cache/photos/39167/catalog_list_39167.jpg",
    "oldPrice": "36.50",
    "newPrice": "21.90",
    "cardPrice": "--.--",
    "quantity": 0
  },
  {
    "id": "5651",
    "name": "Чай (25 ф/п Х 2г) Своя Лінія чорний байховий цейлонський дрібний з ароматом бергамоту",
    "category": "Чай",
    "imageUrl": "https://src.zakaz.atbmarket.com/cache/photos/3692/catalog_list_3692.jpg",
    "oldPrice": "34.90",
    "newPrice": "22.50",
    "cardPrice": "--.--",
    "quantity": 0
  },
  {
    "id": "5479",
    "name": "Чай (25 ф/п х 2г) Своя Лінія чорний байховий дрібний",
    "category": "Чай",
    "imageUrl": "https://src.zakaz.atbmarket.com/cache/photos/35201/catalog_list_35201.jpg",
    "oldPrice": "34.90",
    "newPrice": "22.50",
    "cardPrice": "--.--",
    "quantity": 0
  },
  {
    "id": "26973",
    "name": "Соус 180 г Gusto Сендвич-соус д/пак",
    "category": "Соуси, кетчупи",
    "imageUrl": "https://src.zakaz.atbmarket.com/cache/photos/57779/catalog_list_57779.png",
    "oldPrice": "33.90",
    "newPrice": "22.70",
    "cardPrice": "--.--",
    "quantity": 0
  },
  {
    "id": "33927",
    "name": "Соус 180г Gusto \"Сирний/Cheese\" д/п",
    "category": "Соуси, кетчупи",
    "imageUrl": "https://src.zakaz.atbmarket.com/cache/photos/67543/catalog_list_67543.jpg",
    "oldPrice": "33.90",
    "newPrice": "22.70",
    "cardPrice": "--.--",
    "quantity": 0
  },
  {
    "id": "2268",
    "name": "Пиво 0,5 л Оболонь Світле",
    "category": "Пиво",
    "imageUrl": "https://src.zakaz.atbmarket.com/cache/photos/72315/catalog_list_72315.jpg",
    "oldPrice": "34.40",
    "newPrice": "22.80",
    "cardPrice": "--.--",
    "quantity": 0
  },
  {
    "id": "3259",
    "name": "Напій 250 мл Hell classic plus безалкогольний енергетичний газований",
    "category": "Енергетичні",
    "imageUrl": "https://src.zakaz.atbmarket.com/cache/photos/53641/catalog_list_53641.jpg",
    "oldPrice": "36.90",
    "newPrice": "23.90",
    "cardPrice": "--.--",
    "quantity": 0
  },
  {
    "id": "9774",
    "name": "Насіння соняшника 95 г Сан Санич смажене солоне",
    "category": "Снеки",
    "imageUrl": "https://src.zakaz.atbmarket.com/cache/photos/9719/catalog_list_9719.jpg",
    "oldPrice": "36.80",
    "newPrice": "23.90",
    "cardPrice": "--.--",
    "quantity": 0
  },
  {
    "id": "27353",
    "name": "Грінки житньо-пшеничні 100 г Flint Craft Grenki зі смаком Гострі джерки хвилясті м/уп",
    "category": "Снеки",
    "imageUrl": "https://src.zakaz.atbmarket.com/cache/photos/39165/catalog_list_39165.jpg",
    "oldPrice": "39.90",
    "newPrice": "23.90",
    "cardPrice": "--.--",
    "quantity": 0
  },
  {
    "id": "909",
    "name": "Холодний чай 1л Своя лінія чорний смак персик",
    "category": "Напої",
    "imageUrl": "https://src.zakaz.atbmarket.com/cache/photos/1659/catalog_list_1659.jpg",
    "oldPrice": "34.90",
    "newPrice": "24.40",
    "cardPrice": "--.--",
    "quantity": 0
  },
  {
    "id": "7108",
    "name": "Цукерка 42г Nestle Nuts",
    "category": "Батончики",
    "imageUrl": "https://src.zakaz.atbmarket.com/cache/photos/71037/catalog_list_71037.jpg",
    "oldPrice": "36.30",
    "newPrice": "24.50",
    "cardPrice": "--.--",
    "quantity": 0
  },
  {
    "id": "33531",
    "name": "Морозиво 100 г Ласунка \"ВеликаН\" пломбір ескімо п/ет",
    "category": "Морозиво",
    "imageUrl": "https://src.zakaz.atbmarket.com/cache/photos/66385/catalog_list_66385.jpg",
    "oldPrice": "49.90",
    "newPrice": "24.90",
    "cardPrice": "--.--",
    "quantity": 0
  },
  {
    "id": "38451",
    "name": "Сир кисломолочний 180г День у День 0% еколін",
    "category": "Сир кисломолочний",
    "imageUrl": "https://src.zakaz.atbmarket.com/cache/photos/89601/catalog_list_89601.jpg",
    "oldPrice": "34.40",
    "newPrice": "27.50",
    "cardPrice": "--.--",
    "quantity": 0
  },
  {
    "id": "3035",
    "name": "Напій 0,5л Своя лінія MOVE ON Смак Джин Тонік слабоалкогольний сильногазований",
    "category": "Слабоалкогольні напої",
    "imageUrl": "https://src.zakaz.atbmarket.com/cache/photos/2186/catalog_list_2186.jpg",
    "oldPrice": "37.90",
    "newPrice": "27.50",
    "cardPrice": "--.--",
    "quantity": 0
  },
  {
    "id": "3034",
    "name": "Напій 0,5л Своя лінія MOVE ON Смак Бренді Кола слабоалкогольний сильногазований",
    "category": "Слабоалкогольні напої",
    "imageUrl": "https://src.zakaz.atbmarket.com/cache/photos/2185/catalog_list_2185.jpg",
    "oldPrice": "37.90",
    "newPrice": "27.50",
    "cardPrice": "--.--",
    "quantity": 0
  },
  {
    "id": "2014",
    "name": "Напій 2л Своя Лінія Лимонад",
    "category": "Напої",
    "imageUrl": "https://src.zakaz.atbmarket.com/cache/photos/1798/catalog_list_1798.jpg",
    "oldPrice": "39.90",
    "newPrice": "27.90",
    "cardPrice": "--.--",
    "quantity": 0
  },
  {
    "id": "38453",
    "name": "Сир кисломолочний 180г День у День 5% еколін",
    "category": "Сир кисломолочний",
    "imageUrl": "https://src.zakaz.atbmarket.com/cache/photos/82275/catalog_list_82275.jpg",
    "oldPrice": "35.90",
    "newPrice": "28.50",
    "cardPrice": "--.--",
    "quantity": 0
  },
  {
    "id": "25955",
    "name": "Пиво 0,9 л Чернігівське LIGHT світле ПЕТ",
    "category": "Пиво",
    "imageUrl": "https://src.zakaz.atbmarket.com/cache/photos/75969/catalog_list_75969.jpg",
    "oldPrice": "46.30",
    "newPrice": "28.50",
    "cardPrice": "--.--",
    "quantity": 0
  },
  {
    "id": "38455",
    "name": "Сир кисломолочний 180г День у День 9% еколін",
    "category": "Сир кисломолочний",
    "imageUrl": "https://src.zakaz.atbmarket.com/cache/photos/89603/catalog_list_89603.jpg",
    "oldPrice": "37.90",
    "newPrice": "30.30",
    "cardPrice": "--.--",
    "quantity": 0
  },
  {
    "id": "33527",
    "name": "Kетчуп 380 г Торчин Чилі д/пaк",
    "category": "Соуси, кетчупи",
    "imageUrl": "https://src.zakaz.atbmarket.com/cache/photos/66381/catalog_list_66381.jpg",
    "oldPrice": "44.50",
    "newPrice": "30.90",
    "cardPrice": "--.--",
    "quantity": 0
  },
  {
    "id": "33525",
    "name": "Кетчуп 380 г Торчин Лагідний д/пак",
    "category": "Соуси, кетчупи",
    "imageUrl": "https://src.zakaz.atbmarket.com/cache/photos/73649/catalog_list_73649.jpg",
    "oldPrice": "44.50",
    "newPrice": "30.90",
    "cardPrice": "--.--",
    "quantity": 0
  },
  {
    "id": "33521",
    "name": "Кетчуп 380 г Торчин до Шашлику д/пак",
    "category": "Соуси, кетчупи",
    "imageUrl": "https://src.zakaz.atbmarket.com/cache/photos/66375/catalog_list_66375.jpg",
    "oldPrice": "44.50",
    "newPrice": "30.90",
    "cardPrice": "--.--",
    "quantity": 0
  },
  {
    "id": "42279",
    "name": "Нектар 1 л День у День Мультивітамін, тетра пак",
    "category": "Соки, нектари",
    "imageUrl": "https://src.zakaz.atbmarket.com/cache/photos/94049/catalog_list_94049.jpg",
    "oldPrice": "44.90",
    "newPrice": "31.90",
    "cardPrice": "--.--",
    "quantity": 0
  },
  {
    "id": "42285",
    "name": "Нектар 1л День у День Яблучно - виноградний, тетра пак",
    "category": "Соки, нектари",
    "imageUrl": "https://src.zakaz.atbmarket.com/cache/photos/94055/catalog_list_94055.jpg",
    "oldPrice": "44.90",
    "newPrice": "31.90",
    "cardPrice": "--.--",
    "quantity": 0
  },
  {
    "id": "42283",
    "name": "Нектар 1 л День у День Яблучно - гранатовий, тетра пак",
    "category": "Соки, нектари",
    "imageUrl": "https://src.zakaz.atbmarket.com/cache/photos/94053/catalog_list_94053.jpg",
    "oldPrice": "44.90",
    "newPrice": "31.90",
    "cardPrice": "--.--",
    "quantity": 0
  },
  {
    "id": "42281",
    "name": "Нектар 1 л День у День Мультифруктовий, тетра пак",
    "category": "Соки, нектари",
    "imageUrl": "https://src.zakaz.atbmarket.com/cache/photos/94051/catalog_list_94051.jpg",
    "oldPrice": "44.90",
    "newPrice": "31.90",
    "cardPrice": "--.--",
    "quantity": 0
  },
  {
    "id": "27223",
    "name": "Паста зубна 75 мл Colgate Захист від карієсу к/уп",
    "category": "Гігієна ротової порожнини",
    "imageUrl": "https://src.zakaz.atbmarket.com/cache/photos/38165/catalog_list_38165.jpg",
    "oldPrice": "53.40",
    "newPrice": "32.90",
    "cardPrice": "--.--",
    "quantity": 0
  },
  {
    "id": "972",
    "name": "Рушники паперові 2 шт Своя лінія 2-шарові білі",
    "category": "Серветки, рушники",
    "imageUrl": "https://src.zakaz.atbmarket.com/cache/photos/56655/catalog_list_56655.png",
    "oldPrice": "47.70",
    "newPrice": "33.30",
    "cardPrice": "--.--",
    "quantity": 0
  },
  {
    "id": "41615",
    "name": "Хoлoдний чaй 1,5 л Свoя лінія чopний смaк пepсик ПЕТ",
    "category": "Напої",
    "imageUrl": "https://src.zakaz.atbmarket.com/cache/photos/91587/catalog_list_91587.jpg",
    "oldPrice": "47.90",
    "newPrice": "33.50",
    "cardPrice": "--.--",
    "quantity": 0
  },
  {
    "id": "2593",
    "name": "Прокладки 10 шт Libresse Natural Care Ultra Normal clip",
    "category": "Гігієнічні прокладки/тампони",
    "imageUrl": "https://src.zakaz.atbmarket.com/cache/photos/86595/catalog_list_86595.jpg",
    "oldPrice": "54.30",
    "newPrice": "34.90",
    "cardPrice": "--.--",
    "quantity": 0
  },
  {
    "id": "35127",
    "name": "Сметана 300 г President 10% п/стакан",
    "category": "Сметана",
    "imageUrl": "https://src.zakaz.atbmarket.com/cache/photos/72619/catalog_list_72619.jpg",
    "oldPrice": "48.60",
    "newPrice": "34.90",
    "cardPrice": "--.--",
    "quantity": 0
  },
  {
    "id": "2968",
    "name": "Прокладки 9 шт Libresse Natural Care Ultra Super з екстрактом алое вера та ромашки",
    "category": "Гігієнічні прокладки/тампони",
    "imageUrl": "https://src.zakaz.atbmarket.com/cache/photos/86613/catalog_list_86613.jpg",
    "oldPrice": "54.30",
    "newPrice": "34.90",
    "cardPrice": "--.--",
    "quantity": 0
  },
  {
    "id": "2269",
    "name": "Прокладки 10 шт Libresse Invisible Normal",
    "category": "Гігієнічні прокладки/тампони",
    "imageUrl": "https://src.zakaz.atbmarket.com/cache/photos/86585/catalog_list_86585.jpg",
    "oldPrice": "54.90",
    "newPrice": "35.50",
    "cardPrice": "--.--",
    "quantity": 0
  },
  {
    "id": "27343",
    "name": "Паста зубна 75 мл Colgate відбілювання к/уп",
    "category": "Гігієна ротової порожнини",
    "imageUrl": "https://src.zakaz.atbmarket.com/cache/photos/39145/catalog_list_39145.jpg",
    "oldPrice": "61.50",
    "newPrice": "37.90",
    "cardPrice": "--.--",
    "quantity": 0
  },
  {
    "id": "30187",
    "name": "Шоколад 90 г Roshen Lacmi молочний з начинкою зі смаком полуничної панакоти м/уп",
    "category": "Шоколад",
    "imageUrl": "https://src.zakaz.atbmarket.com/cache/photos/54445/catalog_list_54445.jpg",
    "oldPrice": "67.90",
    "newPrice": "38.50",
    "cardPrice": "--.--",
    "quantity": 0
  },
  {
    "id": "11705",
    "name": "Шоколад 90 г Lacmi молочний з шоколадною начинкою та вафлею",
    "category": "Шоколад",
    "imageUrl": "https://src.zakaz.atbmarket.com/cache/photos/53923/catalog_list_53923.jpg",
    "oldPrice": "67.90",
    "newPrice": "38.50",
    "cardPrice": "--.--",
    "quantity": 0
  },
  {
    "id": "11703",
    "name": "Шоколад 100 г Lacmi молочний з молочною начинкою, карамеллю та печивом з какао",
    "category": "Шоколад",
    "imageUrl": "https://src.zakaz.atbmarket.com/cache/photos/53929/catalog_list_53929.jpg",
    "oldPrice": "67.90",
    "newPrice": "38.50",
    "cardPrice": "--.--",
    "quantity": 0
  },
  {
    "id": "24509",
    "name": "Чипси 125 г Люкс хвилясті зі смаком лисичок м/уп",
    "category": "Чипси",
    "imageUrl": "https://src.zakaz.atbmarket.com/cache/photos/31211/catalog_list_31211.jpg",
    "oldPrice": "64.40",
    "newPrice": "38.50",
    "cardPrice": "--.--",
    "quantity": 0
  },
  {
    "id": "25843",
    "name": "Шоколад 85 г Roshen Lacmi Bubble Crisp молочний пористий з молочною начинкою з кріспі м/уп",
    "category": "Шоколад",
    "imageUrl": "https://src.zakaz.atbmarket.com/cache/photos/53927/catalog_list_53927.jpg",
    "oldPrice": "67.90",
    "newPrice": "38.50",
    "cardPrice": "--.--",
    "quantity": 0
  },
  {
    "id": "30185",
    "name": "Шоколад 87 г Roshen Lacmi молочний з арахісом та карамельно-арахісовою начинкою м/уп",
    "category": "Шоколад",
    "imageUrl": "https://src.zakaz.atbmarket.com/cache/photos/54447/catalog_list_54447.jpg",
    "oldPrice": "67.90",
    "newPrice": "38.50",
    "cardPrice": "--.--",
    "quantity": 0
  },
  {
    "id": "30123",
    "name": "Чипси 125 г Люкс хвилясті зі смаком сметана та цибуля м/уп",
    "category": "Чипси",
    "imageUrl": "https://src.zakaz.atbmarket.com/cache/photos/53919/catalog_list_53919.jpg",
    "oldPrice": "64.40",
    "newPrice": "38.50",
    "cardPrice": "--.--",
    "quantity": 0
  },
  {
    "id": "34617",
    "name": "Горошок 420 г De Luxe Foods&Goods Selected зелений консервований з/б",
    "category": "Овочева та фруктова консервація",
    "imageUrl": "https://src.zakaz.atbmarket.com/cache/photos/69461/catalog_list_69461.png",
    "oldPrice": "51.90",
    "newPrice": "38.50",
    "cardPrice": "--.--",
    "quantity": 0
  },
  {
    "id": "40659",
    "name": "Морозиво 110 г Київський пломбір ваф.ріжок карт/уп",
    "category": "Морозиво",
    "imageUrl": "https://src.zakaz.atbmarket.com/cache/photos/89725/catalog_list_89725.jpg",
    "oldPrice": "64.90",
    "newPrice": "38.90",
    "cardPrice": "--.--",
    "quantity": 0
  },
  {
    "id": "42289",
    "name": "Сік 1 л День у день Томатний відновлений гомогенізований стерилізований тетра-пак",
    "category": "Соки, нектари",
    "imageUrl": "https://src.zakaz.atbmarket.com/cache/photos/94059/catalog_list_94059.jpg",
    "oldPrice": "54.90",
    "newPrice": "38.90",
    "cardPrice": "--.--",
    "quantity": 0
  },
  {
    "id": "24625",
    "name": "Пиво 1,1 л Опілля Експортне 1851 світле ПЕТ",
    "category": "Пиво",
    "imageUrl": "https://src.zakaz.atbmarket.com/cache/photos/74453/catalog_list_74453.jpg",
    "oldPrice": "59.70",
    "newPrice": "39.40",
    "cardPrice": "--.--",
    "quantity": 0
  },
  {
    "id": "7746",
    "name": "Крекер 235г Рошен 2 CRACK з начинкою какао-горіх",
    "category": "Крекери",
    "imageUrl": "https://src.zakaz.atbmarket.com/cache/photos/6864/catalog_list_6864.jpg",
    "oldPrice": "68.70",
    "newPrice": "39.50",
    "cardPrice": "--.--",
    "quantity": 0
  },
  {
    "id": "10400",
    "name": "Крeкeр 235 г Рoшeн 2 CRACK з молочно-ванільною начинкoю",
    "category": "Крекери",
    "imageUrl": "https://src.zakaz.atbmarket.com/cache/photos/11098/catalog_list_11098.jpg",
    "oldPrice": "68.70",
    "newPrice": "39.50",
    "cardPrice": "--.--",
    "quantity": 0
  },
  {
    "id": "3280",
    "name": "Прокладки 10 шт Libresse Ultra нічні",
    "category": "Гігієнічні прокладки/тампони",
    "imageUrl": "https://src.zakaz.atbmarket.com/cache/photos/86627/catalog_list_86627.jpg",
    "oldPrice": "61.90",
    "newPrice": "39.90",
    "cardPrice": "--.--",
    "quantity": 0
  },
  {
    "id": "40473",
    "name": "Млинці 370 г Своя Лінія Французькі з куркою та грибами п/ет",
    "category": "Вареники, Пельмені, Млинці",
    "imageUrl": "https://src.zakaz.atbmarket.com/cache/photos/89145/catalog_list_89145.jpg",
    "oldPrice": "53.90",
    "newPrice": "39.90",
    "cardPrice": "--.--",
    "quantity": 0
  },
  {
    "id": "33517",
    "name": "Рідина для розпалювання 0,5 л Своя лінія, п/уп",
    "category": "Все для Кемпінгу",
    "imageUrl": "https://src.zakaz.atbmarket.com/cache/photos/90217/catalog_list_90217.jpg",
    "oldPrice": "55.50",
    "newPrice": "40.90",
    "cardPrice": "--.--",
    "quantity": 0
  },
  {
    "id": "3468",
    "name": "Кукурудза 340г De Luxe Foods&Goods Selected ніжна",
    "category": "Овочева та фруктова консервація",
    "imageUrl": "https://src.zakaz.atbmarket.com/cache/photos/2425/catalog_list_2425.jpg",
    "oldPrice": "55.90",
    "newPrice": "41.50",
    "cardPrice": "--.--",
    "quantity": 0
  },
  {
    "id": "25959",
    "name": "Освіжувач повітря 250 мл Своя Лінія змінний балон аерозоль",
    "category": "Освіжувачі повітря",
    "imageUrl": "https://src.zakaz.atbmarket.com/cache/photos/92133/catalog_list_92133.jpg",
    "oldPrice": "59.90",
    "newPrice": "41.90",
    "cardPrice": "--.--",
    "quantity": 0
  },
  {
    "id": "2779",
    "name": "Кефір 0,87 кг Галичина Карпатський 2,5%",
    "category": "Кисломолочні напої",
    "imageUrl": "https://src.zakaz.atbmarket.com/cache/photos/2058/catalog_list_2058.jpg",
    "oldPrice": "58.90",
    "newPrice": "42.90",
    "cardPrice": "--.--",
    "quantity": 0
  },
  {
    "id": "35439",
    "name": "Паста зубна 125 мл Colgate Потрійна Дія к/уп",
    "category": "Гігієна ротової порожнини",
    "imageUrl": "https://src.zakaz.atbmarket.com/cache/photos/71829/catalog_list_71829.jpg",
    "oldPrice": "70.90",
    "newPrice": "43.90",
    "cardPrice": "--.--",
    "quantity": 0
  },
  {
    "id": "15",
    "name": "Напій 2 л Coca-Cola безалкoгoльний сильнoгазoваний",
    "category": "Напої",
    "imageUrl": "https://src.zakaz.atbmarket.com/cache/photos/94439/catalog_list_94439.jpg",
    "oldPrice": "57.30",
    "newPrice": "44.10",
    "cardPrice": "--.--",
    "quantity": 0
  },
  {
    "id": "28669",
    "name": "Нaпій 2л Coca-Cola Zero бeзaлкoгoльний сильнoгaзoвaний ПЕТ",
    "category": "Напої",
    "imageUrl": "https://src.zakaz.atbmarket.com/cache/photos/94471/catalog_list_94471.jpg",
    "oldPrice": "57.30",
    "newPrice": "44.10",
    "cardPrice": "--.--",
    "quantity": 0
  },
  {
    "id": "42437",
    "name": "Напій 2л Coca-Cola CHERRY безалкогольний сильногазований ПЕТ",
    "category": "Напої",
    "imageUrl": "https://src.zakaz.atbmarket.com/cache/photos/94513/catalog_list_94513.jpg",
    "oldPrice": "57.30",
    "newPrice": "44.10",
    "cardPrice": "--.--",
    "quantity": 0
  },
  {
    "id": "2665",
    "name": "Дезодорант 50 мл Rexona Invisible aqua антиперспірант кульковий",
    "category": "Дезодоранти",
    "imageUrl": "https://src.zakaz.atbmarket.com/cache/photos/86597/catalog_list_86597.jpg",
    "oldPrice": "74.70",
    "newPrice": "44.50",
    "cardPrice": "--.--",
    "quantity": 0
  },
  {
    "id": "25475",
    "name": "Чай (24 ф/п *2г) Lovare 1001 nights бленд чорного та зеленого з ароматом винограду  з ярликом к/уп",
    "category": "Чай",
    "imageUrl": "https://src.zakaz.atbmarket.com/cache/photos/33571/catalog_list_33571.jpg",
    "oldPrice": "68.60",
    "newPrice": "44.50",
    "cardPrice": "--.--",
    "quantity": 0
  },
  {
    "id": "30567",
    "name": "Чай (24 ф/п х 1,5 г) Lovare зелений Citrus mellisa з ярликом к/уп",
    "category": "Чай",
    "imageUrl": "https://src.zakaz.atbmarket.com/cache/photos/55197/catalog_list_55197.jpg",
    "oldPrice": "68.60",
    "newPrice": "44.50",
    "cardPrice": "--.--",
    "quantity": 0
  },
  {
    "id": "19761",
    "name": "Прокладки гігієнічні Libresse Maxi Goodnight 10шт",
    "category": "Гігієнічні прокладки/тампони",
    "imageUrl": "https://src.zakaz.atbmarket.com/cache/photos/86665/catalog_list_86665.jpg",
    "oldPrice": "69.40",
    "newPrice": "44.90",
    "cardPrice": "--.--",
    "quantity": 0
  },
  {
    "id": "39207",
    "name": "Мило 2в1 4х90 г Своя Лінія Paru Рожеві квіти/Зелений чай м/уп",
    "category": "Мило",
    "imageUrl": "https://src.zakaz.atbmarket.com/cache/photos/85249/catalog_list_85249.jpg",
    "oldPrice": "69.90",
    "newPrice": "44.90",
    "cardPrice": "--.--",
    "quantity": 0
  },
  {
    "id": "39209",
    "name": "Мило 2в1 4х90 г Своя Лінія Paru Морські мінерали м/уп",
    "category": "Мило",
    "imageUrl": "https://src.zakaz.atbmarket.com/cache/photos/85251/catalog_list_85251.jpg",
    "oldPrice": "69.90",
    "newPrice": "44.90",
    "cardPrice": "--.--",
    "quantity": 0
  },
  {
    "id": "32631",
    "name": "Майонез 0,52 кг Торчин Домашний 50% д/пак",
    "category": "Майонез",
    "imageUrl": "https://src.zakaz.atbmarket.com/cache/photos/66227/catalog_list_66227.jpg",
    "oldPrice": "74.90",
    "newPrice": "46.90",
    "cardPrice": "--.--",
    "quantity": 0
  },
  {
    "id": "36015",
    "name": "Консерви 165 г De Luxe Foods & Goods Selected салат з тунцем по мексиканськи з/б",
    "category": "М'ясні та рибні консерви",
    "imageUrl": "https://src.zakaz.atbmarket.com/cache/photos/73777/catalog_list_73777.jpg",
    "oldPrice": "63.90",
    "newPrice": "47.90",
    "cardPrice": "--.--",
    "quantity": 0
  },
  {
    "id": "24617",
    "name": "Сидp 0,95 л Somersby з сoкoм чopниці 4,6% oб ПЕТ",
    "category": "Слабоалкогольні напої",
    "imageUrl": "https://src.zakaz.atbmarket.com/cache/photos/51923/catalog_list_51923.jpg",
    "oldPrice": "75.80",
    "newPrice": "48.90",
    "cardPrice": "--.--",
    "quantity": 0
  },
  {
    "id": "36021",
    "name": "Консерви 165 г De Luxe Foods & Goods Selected салат Тунець з овочами в соусі з/б",
    "category": "М'ясні та рибні консерви",
    "imageUrl": "https://src.zakaz.atbmarket.com/cache/photos/73783/catalog_list_73783.jpg",
    "oldPrice": "66.50",
    "newPrice": "49.70",
    "cardPrice": "--.--",
    "quantity": 0
  },
  {
    "id": "973",
    "name": "Папір туалетний 4 шт Сніжна Панда СуперАбсорб целюлозний двошаровий",
    "category": "Туалетний папір",
    "imageUrl": "https://src.zakaz.atbmarket.com/cache/photos/35157/catalog_list_35157.jpg",
    "oldPrice": "74.40",
    "newPrice": "49.90",
    "cardPrice": "--.--",
    "quantity": 0
  },
  {
    "id": "7844",
    "name": "Пластівці 400г Своя Лінія Fit Active зернові з цільної пшениці",
    "category": "Сухі сніданки",
    "imageUrl": "https://src.zakaz.atbmarket.com/cache/photos/28567/catalog_list_28567.jpg",
    "oldPrice": "66.90",
    "newPrice": "49.90",
    "cardPrice": "--.--",
    "quantity": 0
  },
  {
    "id": "23721",
    "name": "Пиво 1,96 л Holsten Pilsener світлe ПЕТ",
    "category": "Пиво",
    "imageUrl": "https://src.zakaz.atbmarket.com/cache/photos/51947/catalog_list_51947.jpg",
    "oldPrice": "89.50",
    "newPrice": "50.90",
    "cardPrice": "--.--",
    "quantity": 0
  },
  {
    "id": "31545",
    "name": "Майонез 0,52 кг Торчин Європейський 72% д/пак",
    "category": "Майонез",
    "imageUrl": "https://src.zakaz.atbmarket.com/cache/photos/65575/catalog_list_65575.png",
    "oldPrice": "87.90",
    "newPrice": "54.90",
    "cardPrice": "--.--",
    "quantity": 0
  },
  {
    "id": "4185",
    "name": "Сиp напiвтвepдий 135 г Ryki Едам пластини 45%",
    "category": "Сири тверді",
    "imageUrl": "https://src.zakaz.atbmarket.com/cache/photos/2717/catalog_list_2717.jpg",
    "oldPrice": "81.90",
    "newPrice": "55.90",
    "cardPrice": "--.--",
    "quantity": 0
  },
  {
    "id": "4186",
    "name": "Сир напівтвердий 135г Ryki Маасдам пластинками 45%",
    "category": "Сири тверді",
    "imageUrl": "https://src.zakaz.atbmarket.com/cache/photos/2718/catalog_list_2718.jpg",
    "oldPrice": "81.90",
    "newPrice": "55.90",
    "cardPrice": "--.--",
    "quantity": 0
  },
  {
    "id": "26157",
    "name": "Сир напівтвердий 135 г Ryki Цезар 45% пластини газ/упак",
    "category": "Сири тверді",
    "imageUrl": "https://src.zakaz.atbmarket.com/cache/photos/90357/catalog_list_90357.jpg",
    "oldPrice": "81.90",
    "newPrice": "55.90",
    "cardPrice": "--.--",
    "quantity": 0
  },
  {
    "id": "1934",
    "name": "Сир твердий 150г Комо Сметанковий 50%",
    "category": "Сири тверді",
    "imageUrl": "https://src.zakaz.atbmarket.com/cache/photos/76585/catalog_list_76585.jpg",
    "oldPrice": "80.90",
    "newPrice": "56.90",
    "cardPrice": "--.--",
    "quantity": 0
  },
  {
    "id": "20667",
    "name": "Сир твердий 150 г Комо Гауда 45% брусок",
    "category": "Сири тверді",
    "imageUrl": "https://src.zakaz.atbmarket.com/cache/photos/75955/catalog_list_75955.jpg",
    "oldPrice": "80.90",
    "newPrice": "56.90",
    "cardPrice": "--.--",
    "quantity": 0
  },
  {
    "id": "25157",
    "name": "Сир твердий 150 г Комо Вершковий 50% флоу-пак",
    "category": "Сири тверді",
    "imageUrl": "https://src.zakaz.atbmarket.com/cache/photos/75967/catalog_list_75967.jpg",
    "oldPrice": "80.90",
    "newPrice": "56.90",
    "cardPrice": "--.--",
    "quantity": 0
  },
  {
    "id": "36017",
    "name": "Консерви 160 г De Luxe Foods & Goods Selected салат з тунцем та кукурудзою з/б",
    "category": "М'ясні та рибні консерви",
    "imageUrl": "https://src.zakaz.atbmarket.com/cache/photos/73779/catalog_list_73779.jpg",
    "oldPrice": "75.90",
    "newPrice": "56.90",
    "cardPrice": "--.--",
    "quantity": 0
  },
  {
    "id": "36019",
    "name": "Консерви 165 г De Luxe Foods & Goods Selected салат з тунця з французьким соусом з/б",
    "category": "М'ясні та рибні консерви",
    "imageUrl": "https://src.zakaz.atbmarket.com/cache/photos/73781/catalog_list_73781.jpg",
    "oldPrice": "77.50",
    "newPrice": "58.10",
    "cardPrice": "--.--",
    "quantity": 0
  },
  {
    "id": "31931",
    "name": "Пивo 2,4 л Обoлoнь Традиційне Свiтлe ПЕТ",
    "category": "Пиво",
    "imageUrl": "https://src.zakaz.atbmarket.com/cache/photos/93535/catalog_list_93535.jpg",
    "oldPrice": "96.90",
    "newPrice": "59.90",
    "cardPrice": "--.--",
    "quantity": 0
  },
  {
    "id": "2696",
    "name": "Прокладки щоденні 40 шт Libresse Natural Care Normal з екстрактом алое вера та ромашки",
    "category": "Гігієнічні прокладки/тампони",
    "imageUrl": "https://src.zakaz.atbmarket.com/cache/photos/86603/catalog_list_86603.jpg",
    "oldPrice": "96.30",
    "newPrice": "62.50",
    "cardPrice": "--.--",
    "quantity": 0
  },
  {
    "id": "2184",
    "name": "Фігурні вироби 500г Своя лінія Кульки Мікс глазуровані цукровою глазур'ю з какао та молоком",
    "category": "Сухі сніданки",
    "imageUrl": "https://src.zakaz.atbmarket.com/cache/photos/1497/catalog_list_1497.jpg",
    "oldPrice": "87.90",
    "newPrice": "65.50",
    "cardPrice": "--.--",
    "quantity": 0
  },
  {
    "id": "3541",
    "name": "Сир твердий 150г Комо Горіховий 50% з волоським горіхом",
    "category": "Сири тверді",
    "imageUrl": "https://src.zakaz.atbmarket.com/cache/photos/63939/catalog_list_63939.png",
    "oldPrice": "94.20",
    "newPrice": "66.50",
    "cardPrice": "--.--",
    "quantity": 0
  },
  {
    "id": "24229",
    "name": "Олія 0,85 л (782 г) Стожар соняшникова рафінована ПЕТ",
    "category": "Олія та Оцет",
    "imageUrl": "https://src.zakaz.atbmarket.com/cache/photos/57533/catalog_list_57533.png",
    "oldPrice": "80.54",
    "newPrice": "69.90",
    "cardPrice": "--.--",
    "quantity": 0
  },
  {
    "id": "8565",
    "name": "Крекер 235 г Рошен 2 CRACK з шоколадною начинкою",
    "category": "Крекери",
    "imageUrl": "https://src.zakaz.atbmarket.com/cache/photos/7883/catalog_list_7883.jpg",
    "oldPrice": "--.--",
    "newPrice": "71.30",
    "cardPrice": "--.--",
    "quantity": 0
  },
  {
    "id": "29347",
    "name": "Вино 0,75 л ARMEN BAGRANYAN Сапераві червоне сухе 12% об ск/бут Україна",
    "category": "Вино",
    "imageUrl": "https://src.zakaz.atbmarket.com/cache/photos/51965/catalog_list_51965.jpg",
    "oldPrice": "113.70",
    "newPrice": "71.50",
    "cardPrice": "--.--",
    "quantity": 0
  },
  {
    "id": "1753",
    "name": "Ковбаса 0,5 кг М'ясна лавка До пюрешки вар",
    "category": "Ковбаса",
    "imageUrl": "https://src.zakaz.atbmarket.com/cache/photos/1186/catalog_list_1186.png",
    "oldPrice": "123.90",
    "newPrice": "73.90",
    "cardPrice": "--.--",
    "quantity": 0
  },
  {
    "id": "2298",
    "name": "Дезодорант 150 мл Rexona (Прозорий кристал/Блакитний мак та яблуко) жіночий",
    "category": "Дезодоранти",
    "imageUrl": "https://src.zakaz.atbmarket.com/cache/photos/86589/catalog_list_86589.jpg",
    "oldPrice": "125.90",
    "newPrice": "74.90",
    "cardPrice": "--.--",
    "quantity": 0
  },
  {
    "id": "7",
    "name": "Грейпфрут",
    "category": "Фрукти, ягоди",
    "imageUrl": "https://src.zakaz.atbmarket.com/cache/photos/5/catalog_list_5.jpg",
    "oldPrice": "95.95",
    "newPrice": "75.95",
    "cardPrice": "--.--",
    "quantity": 0
  },
  {
    "id": "3076",
    "name": "Дезодорант 150 мл Rexona Men (Невидимий на чорному та білому/Морський бриз)",
    "category": "Дезодоранти",
    "imageUrl": "https://src.zakaz.atbmarket.com/cache/photos/93911/catalog_list_93911.jpg",
    "oldPrice": "128.90",
    "newPrice": "76.90",
    "cardPrice": "--.--",
    "quantity": 0
  },
  {
    "id": "2035",
    "name": "Ковбаса 420 г М'ясна лавка/Своя лінія Губернська н/к",
    "category": "Ковбаса",
    "imageUrl": "https://src.zakaz.atbmarket.com/cache/photos/87453/catalog_list_87453.jpg",
    "oldPrice": "132.90",
    "newPrice": "78.90",
    "cardPrice": "--.--",
    "quantity": 0
  },
  {
    "id": "37665",
    "name": "Вино 0,75 л ARMEN BAGRANYAN Гранат червоне напівсолодке плодове столове 9-12% об ск/бут Україна",
    "category": "Вино",
    "imageUrl": "https://src.zakaz.atbmarket.com/cache/photos/79759/catalog_list_79759.jpg",
    "oldPrice": "125.90",
    "newPrice": "78.90",
    "cardPrice": "--.--",
    "quantity": 0
  },
  {
    "id": "5998",
    "name": "Томати рожеві 1 гат",
    "category": "Овочі",
    "imageUrl": "https://src.zakaz.atbmarket.com/cache/photos/4645/catalog_list_4645.jpg",
    "oldPrice": "94.89",
    "newPrice": "79.89",
    "cardPrice": "--.--",
    "quantity": 0
  },
  {
    "id": "5945",
    "name": "Засіб для миття скла 0,5л Mr Muscle з розпилювачем",
    "category": "Засоби для чищення",
    "imageUrl": "https://src.zakaz.atbmarket.com/cache/photos/24041/catalog_list_24041.jpg",
    "oldPrice": "114.60",
    "newPrice": "79.90",
    "cardPrice": "--.--",
    "quantity": 0
  },
  {
    "id": "17671",
    "name": "Тістечко бісквітне 175 г Мілка з шоколадною начинкою і шматочками молочного шоколаду",
    "category": "Бісквіти та десерти",
    "imageUrl": "https://src.zakaz.atbmarket.com/cache/photos/75953/catalog_list_75953.jpg",
    "oldPrice": "133.90",
    "newPrice": "81.90",
    "cardPrice": "--.--",
    "quantity": 0
  },
  {
    "id": "40703",
    "name": "Морозиво 500 г Три Ведмеді \"Galaretka\" з желейками п/ет",
    "category": "Морозиво",
    "imageUrl": "https://src.zakaz.atbmarket.com/cache/photos/89769/catalog_list_89769.jpg",
    "oldPrice": "139.90",
    "newPrice": "82.90",
    "cardPrice": "--.--",
    "quantity": 0
  },
  {
    "id": "9647",
    "name": "Горілка 0,5 л Хлібний Дар Пшенична Лайт 37,5%",
    "category": "Горілка",
    "imageUrl": "https://src.zakaz.atbmarket.com/cache/photos/27743/catalog_list_27743.jpg",
    "oldPrice": "130.90",
    "newPrice": "83.90",
    "cardPrice": "--.--",
    "quantity": 0
  },
  {
    "id": "1761",
    "name": "Сосиски 450г М'ясна лавка До пюрешки",
    "category": "Сосиски, сардельки",
    "imageUrl": "https://src.zakaz.atbmarket.com/cache/photos/87459/catalog_list_87459.jpg",
    "oldPrice": "121.50",
    "newPrice": "84.90",
    "cardPrice": "--.--",
    "quantity": 0
  },
  {
    "id": "10733",
    "name": "Гомілка курчат-бройлерів Чебатурочка охолоджена",
    "category": "М'ясо охолоджене",
    "imageUrl": "https://src.zakaz.atbmarket.com/cache/photos/38017/catalog_list_38017.jpg",
    "oldPrice": "107.99",
    "newPrice": "86.39",
    "cardPrice": "--.--",
    "quantity": 0
  },
  {
    "id": "11600",
    "name": "Крило курчат-бройлерів Чебатурочка охолоджене",
    "category": "М'ясо охолоджене",
    "imageUrl": "https://src.zakaz.atbmarket.com/cache/photos/11972/catalog_list_11972.jpg",
    "oldPrice": "110.35",
    "newPrice": "87.99",
    "cardPrice": "--.--",
    "quantity": 0
  },
  {
    "id": "4545",
    "name": "Гриби 450г De Luxe Foods&Goods Selected Печериці мaриновані (Польща)",
    "category": "Овочева та фруктова консервація",
    "imageUrl": "https://src.zakaz.atbmarket.com/cache/photos/2837/catalog_list_2837.jpg",
    "oldPrice": "118.90",
    "newPrice": "89.10",
    "cardPrice": "--.--",
    "quantity": 0
  },
  {
    "id": "7823",
    "name": "Гель для прання 2,1 кг WASH & FREE Універсальний",
    "category": "Пральні порошки та засоби для прання",
    "imageUrl": "https://src.zakaz.atbmarket.com/cache/photos/13926/catalog_list_13926.jpg",
    "oldPrice": "145.60",
    "newPrice": "89.90",
    "cardPrice": "--.--",
    "quantity": 0
  },
  {
    "id": "27845",
    "name": "Морозиво 450 г Три Ведмеді Vanilla&Caramel двошарове пласт/лоток",
    "category": "Морозиво",
    "imageUrl": "https://src.zakaz.atbmarket.com/cache/photos/68763/catalog_list_68763.jpg",
    "oldPrice": "164.90",
    "newPrice": "98.90",
    "cardPrice": "--.--",
    "quantity": 0
  },
  {
    "id": "5267",
    "name": "Шампунь 850 мл Romantic Professional регенеруючий",
    "category": "Шампуні",
    "imageUrl": "https://src.zakaz.atbmarket.com/cache/photos/27849/catalog_list_27849.jpg",
    "oldPrice": "149.90",
    "newPrice": "99.90",
    "cardPrice": "--.--",
    "quantity": 0
  },
  {
    "id": "5268",
    "name": "Бальзам для волосся 850 мл Romantic Professional",
    "category": "Догляд за волоссям",
    "imageUrl": "https://src.zakaz.atbmarket.com/cache/photos/27851/catalog_list_27851.jpg",
    "oldPrice": "149.90",
    "newPrice": "99.90",
    "cardPrice": "--.--",
    "quantity": 0
  },
  {
    "id": "3789",
    "name": "Вино 1л Vina Cruz Airen - Sauvignon blanc столове сухе біле ординарне 11%, Іспанія",
    "category": "Вино",
    "imageUrl": "https://src.zakaz.atbmarket.com/cache/photos/32889/catalog_list_32889.jpg",
    "oldPrice": "169.90",
    "newPrice": "118.90",
    "cardPrice": "--.--",
    "quantity": 0
  },
  {
    "id": "3790",
    "name": "Вино 1л Vina Cruz Tempranillo столове сухе червоне ординарне 12%, Іспанія",
    "category": "Вино",
    "imageUrl": "https://src.zakaz.atbmarket.com/cache/photos/32891/catalog_list_32891.jpg",
    "oldPrice": "169.90",
    "newPrice": "118.90",
    "cardPrice": "--.--",
    "quantity": 0
  },
  {
    "id": "33585",
    "name": "Брикети деревновугільні 2 кг Своя лінія, бум/уп",
    "category": "Все для Кемпінгу",
    "imageUrl": "https://src.zakaz.atbmarket.com/cache/photos/91971/catalog_list_91971.jpg",
    "oldPrice": "168.90",
    "newPrice": "124.00",
    "cardPrice": "--.--",
    "quantity": 0
  },
  {
    "id": "8486",
    "name": "Горілка 0,7 л Biala ТМ Zubrowka 40%",
    "category": "Горілка",
    "imageUrl": "https://src.zakaz.atbmarket.com/cache/photos/24805/catalog_list_24805.jpg",
    "oldPrice": "189.90",
    "newPrice": "134.50",
    "cardPrice": "--.--",
    "quantity": 0
  },
  {
    "id": "38691",
    "name": "Вермут 1 л De Luxe Foods & Goods Selected білий солодкий 15% об ск/бут Італія",
    "category": "Вермут",
    "imageUrl": "https://src.zakaz.atbmarket.com/cache/photos/82837/catalog_list_82837.jpg",
    "oldPrice": "229.90",
    "newPrice": "143.90",
    "cardPrice": "--.--",
    "quantity": 0
  },
  {
    "id": "27985",
    "name": "Цукерки Своя Лінія Waffle candy вафельні зі смаком шоколаду вагові",
    "category": "Цукерки",
    "imageUrl": "https://src.zakaz.atbmarket.com/cache/photos/51233/catalog_list_51233.jpg",
    "oldPrice": "230.99",
    "newPrice": "144.90",
    "cardPrice": "--.--",
    "quantity": 0
  },
  {
    "id": "33955",
    "name": "Засіб миючий синтетичний 1,2 кг Persil універсальний порошок в асортименті м/уп",
    "category": "Пральні порошки та засоби для прання",
    "imageUrl": "https://src.zakaz.atbmarket.com/cache/photos/67571/catalog_list_67571.jpg",
    "oldPrice": "255.40",
    "newPrice": "145.00",
    "cardPrice": "--.--",
    "quantity": 0
  },
  {
    "id": "7817",
    "name": "Горілка 0,7л Bison Grass ТМ Zubrowka 37,5%",
    "category": "Горілка",
    "imageUrl": "https://src.zakaz.atbmarket.com/cache/photos/24791/catalog_list_24791.jpg",
    "oldPrice": "213.90",
    "newPrice": "151.50",
    "cardPrice": "--.--",
    "quantity": 0
  },
  {
    "id": "16367",
    "name": "Засіб миючий синтетичний 19 шт WASH & FREE рідкий в розчинних капсулах",
    "category": "Пральні порошки та засоби для прання",
    "imageUrl": "https://src.zakaz.atbmarket.com/cache/photos/21929/catalog_list_21929.jpg",
    "oldPrice": "253.90",
    "newPrice": "157.00",
    "cardPrice": "--.--",
    "quantity": 0
  },
  {
    "id": "8022",
    "name": "Хек тушка",
    "category": "Риба",
    "imageUrl": "https://src.zakaz.atbmarket.com/cache/photos/87609/catalog_list_87609.jpg",
    "oldPrice": "198.45",
    "newPrice": "158.50",
    "cardPrice": "--.--",
    "quantity": 0
  },
  {
    "id": "38217",
    "name": "Лікер 0,5 л Krupnik капучино 16% об ск/пл Польща",
    "category": "Лікери, настоянки, бальзами",
    "imageUrl": "https://src.zakaz.atbmarket.com/cache/photos/81107/catalog_list_81107.jpg",
    "oldPrice": "219.90",
    "newPrice": "159.90",
    "cardPrice": "--.--",
    "quantity": 0
  },
  {
    "id": "37139",
    "name": "Кава 250 г Eilles Kaffee Exclusive натуральна смажена мелена, вак/уп",
    "category": "Кава, какао",
    "imageUrl": "https://src.zakaz.atbmarket.com/cache/photos/77275/catalog_list_77275.jpg",
    "oldPrice": "249.90",
    "newPrice": "174.90",
    "cardPrice": "--.--",
    "quantity": 0
  },
  {
    "id": "33573",
    "name": "Шампунь 0,5 л Head&Shoulders 2в1 Осн. догляд/Свіжість ментолу/Глибоке зволоження/Ябл. свіжість п/фл",
    "category": "Шампуні",
    "imageUrl": "https://src.zakaz.atbmarket.com/cache/photos/66435/catalog_list_66435.jpg",
    "oldPrice": "269.50",
    "newPrice": "179.00",
    "cardPrice": "--.--",
    "quantity": 0
  },
  {
    "id": "11690",
    "name": "Креветки 0,9 кг Своя Лінія нерозібрані варено-морожені глазуровані 70/90",
    "category": "Морепродукти",
    "imageUrl": "https://src.zakaz.atbmarket.com/cache/photos/12114/catalog_list_12114.jpg",
    "oldPrice": "258.90",
    "newPrice": "189.90",
    "cardPrice": "--.--",
    "quantity": 0
  },
  {
    "id": "2094",
    "name": "Алкогольний напій з ромом 0,7л The Colonist Spiced Black 40%",
    "category": "Інший алкоголь",
    "imageUrl": "https://src.zakaz.atbmarket.com/cache/photos/24797/catalog_list_24797.jpg",
    "oldPrice": "319.90",
    "newPrice": "233.90",
    "cardPrice": "--.--",
    "quantity": 0
  },
  {
    "id": "30905",
    "name": "Засіб миючий синтетичний 2,7 кг Gala Aqua Puder Color Французький аромат м/уп",
    "category": "Пральні порошки та засоби для прання",
    "imageUrl": "https://src.zakaz.atbmarket.com/cache/photos/60923/catalog_list_60923.png",
    "oldPrice": "430.40",
    "newPrice": "255.00",
    "cardPrice": "--.--",
    "quantity": 0
  },
  {
    "id": "7186",
    "name": "Філе Своя лінія куряче",
    "category": "Нарізки та делікатеси",
    "imageUrl": "https://src.zakaz.atbmarket.com/cache/photos/9404/catalog_list_9404.jpg",
    "oldPrice": "360.85",
    "newPrice": "266.99",
    "cardPrice": "--.--",
    "quantity": 0
  },
  {
    "id": "37141",
    "name": "Кава 500 г Eilles Gourmet Cafe натуральна смажена мелена, вак/уп",
    "category": "Кава, какао",
    "imageUrl": "https://src.zakaz.atbmarket.com/cache/photos/77277/catalog_list_77277.jpg",
    "oldPrice": "429.90",
    "newPrice": "299.90",
    "cardPrice": "--.--",
    "quantity": 0
  },
  {
    "id": "822",
    "name": "Балик Своя лінія Святковий",
    "category": "Нарізки та делікатеси",
    "imageUrl": "https://src.zakaz.atbmarket.com/cache/photos/26457/catalog_list_26457.jpg",
    "oldPrice": "455.49",
    "newPrice": "316.99",
    "cardPrice": "--.--",
    "quantity": 0
  },
  {
    "id": "5191",
    "name": "Ковбаса М'ясна лавка/Своя лінія Салямі Баварська с/к",
    "category": "Ковбаса",
    "imageUrl": "https://src.zakaz.atbmarket.com/cache/photos/3075/catalog_list_3075.jpg",
    "oldPrice": "573.49",
    "newPrice": "340.99",
    "cardPrice": "--.--",
    "quantity": 0
  },
  {
    "id": "27103",
    "name": "Віскі 0,7 л Jameson 40% об ск/бут",
    "category": "Інший алкоголь",
    "imageUrl": "https://src.zakaz.atbmarket.com/cache/photos/45347/catalog_list_45347.jpg",
    "oldPrice": "885.80",
    "newPrice": "579.90",
    "cardPrice": "--.--",
    "quantity": 0
  },
  {
    "id": "8516",
    "name": "Кава 1000 г Kavos Bankas Espresso Italiano в зернах",
    "category": "Кава, какао",
    "imageUrl": "https://src.zakaz.atbmarket.com/cache/photos/7834/catalog_list_7834.jpg",
    "oldPrice": "849.90",
    "newPrice": "629.90",
    "cardPrice": "--.--",
    "quantity": 0
  }
]