[
  {
    "id": "38457",
    "name": "Сирок глазурований 36 г День у День з вареним згущеним молоком 15% фольга",
    "category": "Сирки глазуровані",
    "imageUrl": "https://src.zakaz.atbmarket.com/cache/photos/83333/catalog_list_83333.jpg",
    "oldPrice": "12.90",
    "newPrice": "9.90",
    "cardPrice": "--.--",
    "quantity": 0
  },
  {
    "id": "38461",
    "name": "Сирок глазурований 36 г День у День Полуниця 15% фольга",
    "category": "Сирки глазуровані",
    "imageUrl": "https://src.zakaz.atbmarket.com/cache/photos/83337/catalog_list_83337.jpg",
    "oldPrice": "12.90",
    "newPrice": "9.90",
    "cardPrice": "--.--",
    "quantity": 0
  },
  {
    "id": "38459",
    "name": "Сирок глазурований 36 г День у День Кокос 20% фольга",
    "category": "Сирки глазуровані",
    "imageUrl": "https://src.zakaz.atbmarket.com/cache/photos/83335/catalog_list_83335.jpg",
    "oldPrice": "12.90",
    "newPrice": "9.90",
    "cardPrice": "--.--",
    "quantity": 0
  },
  {
    "id": "26907",
    "name": "Вафлі 71 г Своя Лінія Молочні-клас! з ароматом молока м/уп",
    "category": "Вафлі",
    "imageUrl": "https://src.zakaz.atbmarket.com/cache/photos/93069/catalog_list_93069.jpg",
    "oldPrice": "16.60",
    "newPrice": "11.50",
    "cardPrice": "--.--",
    "quantity": 0
  },
  {
    "id": "37867",
    "name": "Вафлі 71 г Своя Лінія Артек-клас! м/уп",
    "category": "Вафлі",
    "imageUrl": "https://src.zakaz.atbmarket.com/cache/photos/80357/catalog_list_80357.jpg",
    "oldPrice": "16.60",
    "newPrice": "11.50",
    "cardPrice": "--.--",
    "quantity": 0
  },
  {
    "id": "26905",
    "name": "Вафлі 71 г Своя Лінія з ароматом шоколад м/уп",
    "category": "Вафлі",
    "imageUrl": "https://src.zakaz.atbmarket.com/cache/photos/60583/catalog_list_60583.png",
    "oldPrice": "16.60",
    "newPrice": "11.50",
    "cardPrice": "--.--",
    "quantity": 0
  },
  {
    "id": "24015",
    "name": "Сирок кисломолочний 90 г Milupa з біфідобактеріями 4% п/стакан",
    "category": "Дитяча молочна продукція",
    "imageUrl": "https://src.zakaz.atbmarket.com/cache/photos/75961/catalog_list_75961.jpg",
    "oldPrice": "18.50",
    "newPrice": "13.30",
    "cardPrice": "--.--",
    "quantity": 0
  },
  {
    "id": "23931",
    "name": "Сирок 90 г Milupa Банан-абрикос без цукру 3% п/стакан",
    "category": "Дитяча молочна продукція",
    "imageUrl": "https://src.zakaz.atbmarket.com/cache/photos/29805/catalog_list_29805.jpg",
    "oldPrice": "19.50",
    "newPrice": "13.90",
    "cardPrice": "--.--",
    "quantity": 0
  },
  {
    "id": "24013",
    "name": "Сирок 90 г Milupa Банан-суниця без цукру 3% п/стакан",
    "category": "Дитяча молочна продукція",
    "imageUrl": "https://src.zakaz.atbmarket.com/cache/photos/30127/catalog_list_30127.jpg",
    "oldPrice": "19.50",
    "newPrice": "13.90",
    "cardPrice": "--.--",
    "quantity": 0
  },
  {
    "id": "12889",
    "name": "Вoдa 0,75 л Свoя Лінія Тpускaвeцькa Спорт нeгaзoвaнa",
    "category": "Мінеральна і питна вода",
    "imageUrl": "https://src.zakaz.atbmarket.com/cache/photos/13879/catalog_list_13879.jpg",
    "oldPrice": "17.50",
    "newPrice": "13.90",
    "cardPrice": "--.--",
    "quantity": 0
  },
  {
    "id": "2292",
    "name": "Напій 0,5л Живчик газований",
    "category": "Напої",
    "imageUrl": "https://src.zakaz.atbmarket.com/cache/photos/69451/catalog_list_69451.jpg",
    "oldPrice": "22.60",
    "newPrice": "14.70",
    "cardPrice": "--.--",
    "quantity": 0
  },
  {
    "id": "24707",
    "name": "Напій кисломолочний йогуртний 100 г Лактонія Імун+ малина-ехінацея 1,5% п/бут",
    "category": "Йогурти",
    "imageUrl": "https://src.zakaz.atbmarket.com/cache/photos/31585/catalog_list_31585.jpg",
    "oldPrice": "21.90",
    "newPrice": "15.30",
    "cardPrice": "--.--",
    "quantity": 0
  },
  {
    "id": "29341",
    "name": "Напій кисломолочний йогуртний 100 г Лактонія Імун+ полуниця 1,5% п/бут",
    "category": "Йогурти",
    "imageUrl": "https://src.zakaz.atbmarket.com/cache/photos/52519/catalog_list_52519.jpg",
    "oldPrice": "21.90",
    "newPrice": "15.30",
    "cardPrice": "--.--",
    "quantity": 0
  },
  {
    "id": "13316",
    "name": "Сир плавлений 70 г Своя Лінія Вершковий 55%",
    "category": "Сири плавлені",
    "imageUrl": "https://src.zakaz.atbmarket.com/cache/photos/14976/catalog_list_14976.jpg",
    "oldPrice": "21.90",
    "newPrice": "15.90",
    "cardPrice": "--.--",
    "quantity": 0
  },
  {
    "id": "13315",
    "name": "Сир плавлений 70 г Своя Лінія Дружба 55%",
    "category": "Сири плавлені",
    "imageUrl": "https://src.zakaz.atbmarket.com/cache/photos/14975/catalog_list_14975.jpg",
    "oldPrice": "21.90",
    "newPrice": "15.90",
    "cardPrice": "--.--",
    "quantity": 0
  },
  {
    "id": "28741",
    "name": "Батончик 39 г Roshen Double Peanuts молочний шоколад з арахісом м/уп",
    "category": "Батончики",
    "imageUrl": "https://src.zakaz.atbmarket.com/cache/photos/50085/catalog_list_50085.jpg",
    "oldPrice": "22.80",
    "newPrice": "16.50",
    "cardPrice": "--.--",
    "quantity": 0
  },
  {
    "id": "1014",
    "name": "Батончик 43г Рошен молочно-шоколадний з начинкою крем-брюле",
    "category": "Батончики",
    "imageUrl": "https://src.zakaz.atbmarket.com/cache/photos/722/catalog_list_722.jpg",
    "oldPrice": "22.80",
    "newPrice": "16.50",
    "cardPrice": "--.--",
    "quantity": 0
  },
  {
    "id": "1016",
    "name": "Батончик 43г Рошен з начинкою",
    "category": "Батончики",
    "imageUrl": "https://src.zakaz.atbmarket.com/cache/photos/724/catalog_list_724.jpg",
    "oldPrice": "22.80",
    "newPrice": "16.50",
    "cardPrice": "--.--",
    "quantity": 0
  },
  {
    "id": "26983",
    "name": "Батончик 38 г Roshen з кокосом та мигдалем м/уп",
    "category": "Батончики",
    "imageUrl": "https://src.zakaz.atbmarket.com/cache/photos/37513/catalog_list_37513.jpg",
    "oldPrice": "22.80",
    "newPrice": "16.50",
    "cardPrice": "--.--",
    "quantity": 0
  },
  {
    "id": "34055",
    "name": "Йогурт 207 г Milupa полуниця-банан 2,1% п/пак",
    "category": "Дитяча молочна продукція",
    "imageUrl": "https://src.zakaz.atbmarket.com/cache/photos/98139/catalog_list_98139.jpg",
    "oldPrice": "22.90",
    "newPrice": "17.00",
    "cardPrice": "--.--",
    "quantity": 0
  },
  {
    "id": "34061",
    "name": "Йогурт 207 г Milupa малина з біфідобактеріями 2,1% п/пак",
    "category": "Дитяча молочна продукція",
    "imageUrl": "https://src.zakaz.atbmarket.com/cache/photos/98141/catalog_list_98141.jpg",
    "oldPrice": "22.90",
    "newPrice": "17.00",
    "cardPrice": "--.--",
    "quantity": 0
  },
  {
    "id": "34053",
    "name": "Йогурт 207 г Milupa банан-суниця 2,1% п/пак",
    "category": "Дитяча молочна продукція",
    "imageUrl": "https://src.zakaz.atbmarket.com/cache/photos/98137/catalog_list_98137.jpg",
    "oldPrice": "22.90",
    "newPrice": "17.00",
    "cardPrice": "--.--",
    "quantity": 0
  },
  {
    "id": "35173",
    "name": "Нaпій 0,5 л Pit Bull Exotic eнepгeтичний бeзaлкoгoльний ж/б",
    "category": "Енергетичні",
    "imageUrl": "https://src.zakaz.atbmarket.com/cache/photos/72657/catalog_list_72657.jpg",
    "oldPrice": "29.70",
    "newPrice": "19.90",
    "cardPrice": "--.--",
    "quantity": 0
  },
  {
    "id": "11342",
    "name": "Морозиво 75 г  Хрещатик на печиві з какао сендвіч",
    "category": "Морозиво",
    "imageUrl": "https://src.zakaz.atbmarket.com/cache/photos/47283/catalog_list_47283.jpg",
    "oldPrice": "37.50",
    "newPrice": "19.90",
    "cardPrice": "--.--",
    "quantity": 0
  },
  {
    "id": "42339",
    "name": "Майонезний соус 300 г Своя лінія Легкий 28% д/пак",
    "category": "Майонез",
    "imageUrl": "https://src.zakaz.atbmarket.com/cache/photos/94127/catalog_list_94127.jpg",
    "oldPrice": "30.50",
    "newPrice": "21.30",
    "cardPrice": "--.--",
    "quantity": 0
  },
  {
    "id": "9949",
    "name": "Йогурт 290 г Лактонія Висівки-злаки 1,5%",
    "category": "Йогурти",
    "imageUrl": "https://src.zakaz.atbmarket.com/cache/photos/79531/catalog_list_79531.jpg",
    "oldPrice": "33.70",
    "newPrice": "23.50",
    "cardPrice": "--.--",
    "quantity": 0
  },
  {
    "id": "9950",
    "name": "Йогурт 290 г Лактонія Персик 1,5%",
    "category": "Йогурти",
    "imageUrl": "https://src.zakaz.atbmarket.com/cache/photos/79533/catalog_list_79533.jpg",
    "oldPrice": "33.70",
    "newPrice": "23.50",
    "cardPrice": "--.--",
    "quantity": 0
  },
  {
    "id": "36273",
    "name": "Нaпій 1,15 л Живчик з соком яблука гaзoвaний ПЕТ",
    "category": "Напої",
    "imageUrl": "https://src.zakaz.atbmarket.com/cache/photos/74603/catalog_list_74603.jpg",
    "oldPrice": "36.90",
    "newPrice": "23.90",
    "cardPrice": "--.--",
    "quantity": 0
  },
  {
    "id": "21699",
    "name": "Соус 200 г Торчин Шаурма",
    "category": "Соуси, кетчупи",
    "imageUrl": "https://src.zakaz.atbmarket.com/cache/photos/57269/catalog_list_57269.png",
    "oldPrice": "35.00",
    "newPrice": "24.50",
    "cardPrice": "--.--",
    "quantity": 0
  },
  {
    "id": "4414",
    "name": "Соус 200г Торчин Бургер",
    "category": "Соуси, кетчупи",
    "imageUrl": "https://src.zakaz.atbmarket.com/cache/photos/57253/catalog_list_57253.png",
    "oldPrice": "35.00",
    "newPrice": "24.50",
    "cardPrice": "--.--",
    "quantity": 0
  },
  {
    "id": "2803",
    "name": "Соус 200г Торчин Сацебелі",
    "category": "Соуси, кетчупи",
    "imageUrl": "https://src.zakaz.atbmarket.com/cache/photos/57247/catalog_list_57247.png",
    "oldPrice": "35.00",
    "newPrice": "24.50",
    "cardPrice": "--.--",
    "quantity": 0
  },
  {
    "id": "26671",
    "name": "Пиво 0,5 л Lowenbrau Original Світлe ск/бут",
    "category": "Пиво",
    "imageUrl": "https://src.zakaz.atbmarket.com/cache/photos/36251/catalog_list_36251.jpg",
    "oldPrice": "43.60",
    "newPrice": "24.80",
    "cardPrice": "--.--",
    "quantity": 0
  },
  {
    "id": "38481",
    "name": "Засіб миючий для посуду 0,5 л День у День бальзам Зелене яблуко/Авокадо і алое дойпак",
    "category": "Засоби для миття посуду",
    "imageUrl": "https://src.zakaz.atbmarket.com/cache/photos/82313/catalog_list_82313.jpg",
    "oldPrice": "35.90",
    "newPrice": "24.90",
    "cardPrice": "--.--",
    "quantity": 0
  },
  {
    "id": "6794",
    "name": "Пивo бeзaлкoгoльнe 0,5л Обoлoнь 0 світлe нефільтроване пaстepизoвaнe",
    "category": "Пиво",
    "imageUrl": "https://src.zakaz.atbmarket.com/cache/photos/5361/catalog_list_5361.jpg",
    "oldPrice": "37.90",
    "newPrice": "25.00",
    "cardPrice": "--.--",
    "quantity": 0
  },
  {
    "id": "14691",
    "name": "Пивo 0,5 л Чepнігівськe Білe",
    "category": "Пиво",
    "imageUrl": "https://src.zakaz.atbmarket.com/cache/photos/80335/catalog_list_80335.jpg",
    "oldPrice": "39.60",
    "newPrice": "26.00",
    "cardPrice": "--.--",
    "quantity": 0
  },
  {
    "id": "8479",
    "name": "Печиво 135 г Рошен Lovita здобне с желейною начинкою зі смаком апельсину м/уп",
    "category": "Печиво, пряники",
    "imageUrl": "https://src.zakaz.atbmarket.com/cache/photos/7727/catalog_list_7727.jpg",
    "oldPrice": "39.80",
    "newPrice": "26.50",
    "cardPrice": "--.--",
    "quantity": 0
  },
  {
    "id": "8478",
    "name": "Печиво 135 г Рошен Lovita здобне с желейною начинкою зі смаком малини м/уп",
    "category": "Печиво, пряники",
    "imageUrl": "https://src.zakaz.atbmarket.com/cache/photos/7726/catalog_list_7726.jpg",
    "oldPrice": "39.80",
    "newPrice": "26.50",
    "cardPrice": "--.--",
    "quantity": 0
  },
  {
    "id": "3031",
    "name": "Прокладки щоденні 20 шт Bella Panty Classic",
    "category": "Гігієнічні прокладки/тампони",
    "imageUrl": "https://src.zakaz.atbmarket.com/cache/photos/4809/catalog_list_4809.jpg",
    "oldPrice": "41.50",
    "newPrice": "26.90",
    "cardPrice": "--.--",
    "quantity": 0
  },
  {
    "id": "42333",
    "name": "Майонез 300г Своя Лінія 50% Смачний д/пак",
    "category": "Майонез",
    "imageUrl": "https://src.zakaz.atbmarket.com/cache/photos/95363/catalog_list_95363.png",
    "oldPrice": "38.60",
    "newPrice": "26.90",
    "cardPrice": "--.--",
    "quantity": 0
  },
  {
    "id": "617",
    "name": "Чай (25 ф/п х 2г) Alokozay чорний",
    "category": "Чай",
    "imageUrl": "https://src.zakaz.atbmarket.com/cache/photos/437/catalog_list_437.jpg",
    "oldPrice": "42.40",
    "newPrice": "27.50",
    "cardPrice": "--.--",
    "quantity": 0
  },
  {
    "id": "14961",
    "name": "Серветки кoсметичні 100+50 шт Своя лінія універсальні двoшарoві",
    "category": "Серветки, рушники",
    "imageUrl": "https://src.zakaz.atbmarket.com/cache/photos/76537/catalog_list_76537.jpg",
    "oldPrice": "39.90",
    "newPrice": "27.90",
    "cardPrice": "--.--",
    "quantity": 0
  },
  {
    "id": "9585",
    "name": "Чипси 100 г El Sabor Начо кукурудзяні зі смаком барбекю",
    "category": "Чипси",
    "imageUrl": "https://src.zakaz.atbmarket.com/cache/photos/95081/catalog_list_95081.jpg",
    "oldPrice": "43.50",
    "newPrice": "28.10",
    "cardPrice": "--.--",
    "quantity": 0
  },
  {
    "id": "9584",
    "name": "Чипси 100 г El Sabor Начо кукурудзяні зі смаком сиру",
    "category": "Чипси",
    "imageUrl": "https://src.zakaz.atbmarket.com/cache/photos/95079/catalog_list_95079.jpg",
    "oldPrice": "43.50",
    "newPrice": "28.10",
    "cardPrice": "--.--",
    "quantity": 0
  },
  {
    "id": "32605",
    "name": "Чай ((20+2)*1,6г) LOVARE Імбирний ранок суміш чаю трав'яного та ягідного з імбирем та лимоном к/уп",
    "category": "Чай",
    "imageUrl": "https://src.zakaz.atbmarket.com/cache/photos/66209/catalog_list_66209.jpg",
    "oldPrice": "48.70",
    "newPrice": "29.20",
    "cardPrice": "--.--",
    "quantity": 0
  },
  {
    "id": "2014",
    "name": "Напій 2л Своя Лінія Лимонад",
    "category": "Напої",
    "imageUrl": "https://src.zakaz.atbmarket.com/cache/photos/1798/catalog_list_1798.jpg",
    "oldPrice": "39.90",
    "newPrice": "29.90",
    "cardPrice": "--.--",
    "quantity": 0
  },
  {
    "id": "35685",
    "name": "Серветки вологі дитячі 72 шт Своя лінія Mini Bee з екстрактом череди, ромашки, календули м/уп",
    "category": "Серветки вологі",
    "imageUrl": "https://src.zakaz.atbmarket.com/cache/photos/72591/catalog_list_72591.jpg",
    "oldPrice": "44.90",
    "newPrice": "31.30",
    "cardPrice": "--.--",
    "quantity": 0
  },
  {
    "id": "13029",
    "name": "Нaпій 2 л Своя Лінія Lemon бeзaлкoгoльний сильнoгaзoвaний",
    "category": "Напої",
    "imageUrl": "https://src.zakaz.atbmarket.com/cache/photos/14173/catalog_list_14173.jpg",
    "oldPrice": "41.90",
    "newPrice": "31.40",
    "cardPrice": "--.--",
    "quantity": 0
  },
  {
    "id": "13030",
    "name": "Нaпій 2 л Своя Лінія Orange бeзaлкoгoльний сильнoгaзoвaний",
    "category": "Напої",
    "imageUrl": "https://src.zakaz.atbmarket.com/cache/photos/14174/catalog_list_14174.jpg",
    "oldPrice": "41.90",
    "newPrice": "31.40",
    "cardPrice": "--.--",
    "quantity": 0
  },
  {
    "id": "15103",
    "name": "Яблуко Гала",
    "category": "Фрукти, ягоди",
    "imageUrl": "https://src.zakaz.atbmarket.com/cache/photos/19441/catalog_list_19441.png",
    "oldPrice": "38.95",
    "newPrice": "31.95",
    "cardPrice": "--.--",
    "quantity": 0
  },
  {
    "id": "41143",
    "name": "Морозиво 150 г Три Ведмеді \"love&caramel\" двошарове ваф.ріжок п/ет",
    "category": "Морозиво",
    "imageUrl": "https://src.zakaz.atbmarket.com/cache/photos/90349/catalog_list_90349.jpg",
    "oldPrice": "59.90",
    "newPrice": "32.90",
    "cardPrice": "--.--",
    "quantity": 0
  },
  {
    "id": "32897",
    "name": "Нaпій 2 л Живчик Яблуко та Лісові ягоди гaзoвaний ПЕТ",
    "category": "Напої",
    "imageUrl": "https://src.zakaz.atbmarket.com/cache/photos/64103/catalog_list_64103.jpg",
    "oldPrice": "53.80",
    "newPrice": "34.90",
    "cardPrice": "--.--",
    "quantity": 0
  },
  {
    "id": "43181",
    "name": "Чай 60 г Своя Лінія Soursop зелений листовий з додаванням шматочків плодів ароматизований, м/уп",
    "category": "Чай",
    "imageUrl": "https://src.zakaz.atbmarket.com/cache/photos/98181/catalog_list_98181.jpg",
    "oldPrice": "49.90",
    "newPrice": "34.90",
    "cardPrice": "--.--",
    "quantity": 0
  },
  {
    "id": "25843",
    "name": "Шоколад 85 г Roshen Lacmi Fun&Crispy молочний пористий з молочною начинкою з кріспі м/уп",
    "category": "Шоколад",
    "imageUrl": "https://src.zakaz.atbmarket.com/cache/photos/99809/catalog_list_99809.jpg",
    "oldPrice": "67.90",
    "newPrice": "35.50",
    "cardPrice": "--.--",
    "quantity": 0
  },
  {
    "id": "11705",
    "name": "Шоколад 90 г Lacmi молочний з шоколадною начинкою та вафлею",
    "category": "Шоколад",
    "imageUrl": "https://src.zakaz.atbmarket.com/cache/photos/53923/catalog_list_53923.jpg",
    "oldPrice": "67.90",
    "newPrice": "35.50",
    "cardPrice": "--.--",
    "quantity": 0
  },
  {
    "id": "11703",
    "name": "Шоколад 100 г Lacmi молочний з молочною начинкою, карамеллю та печивом з какао",
    "category": "Шоколад",
    "imageUrl": "https://src.zakaz.atbmarket.com/cache/photos/53929/catalog_list_53929.jpg",
    "oldPrice": "67.90",
    "newPrice": "35.50",
    "cardPrice": "--.--",
    "quantity": 0
  },
  {
    "id": "30185",
    "name": "Шоколад 87 г Roshen Lacmi молочний з арахісом та карамельно-арахісовою начинкою м/уп",
    "category": "Шоколад",
    "imageUrl": "https://src.zakaz.atbmarket.com/cache/photos/54447/catalog_list_54447.jpg",
    "oldPrice": "67.90",
    "newPrice": "35.50",
    "cardPrice": "--.--",
    "quantity": 0
  },
  {
    "id": "30187",
    "name": "Шоколад 90 г Roshen Lacmi молочний з начинкою зі смаком полуничної панакоти м/уп",
    "category": "Шоколад",
    "imageUrl": "https://src.zakaz.atbmarket.com/cache/photos/54445/catalog_list_54445.jpg",
    "oldPrice": "67.90",
    "newPrice": "35.50",
    "cardPrice": "--.--",
    "quantity": 0
  },
  {
    "id": "968",
    "name": "Папір туалетний 4 шт Своя лінія жовтий двошаровий на гільзі",
    "category": "Туалетний папір",
    "imageUrl": "https://src.zakaz.atbmarket.com/cache/photos/56865/catalog_list_56865.png",
    "oldPrice": "50.90",
    "newPrice": "35.90",
    "cardPrice": "--.--",
    "quantity": 0
  },
  {
    "id": "42331",
    "name": "Майонез 300 г Своя лінія Європейский 72% д/пак",
    "category": "Майонез",
    "imageUrl": "https://src.zakaz.atbmarket.com/cache/photos/94119/catalog_list_94119.png",
    "oldPrice": "52.40",
    "newPrice": "36.30",
    "cardPrice": "--.--",
    "quantity": 0
  },
  {
    "id": "894",
    "name": "Корм 300г Friskies сухий Курка з овочами",
    "category": "Корм",
    "imageUrl": "https://src.zakaz.atbmarket.com/cache/photos/92439/catalog_list_92439.jpg",
    "oldPrice": "56.50",
    "newPrice": "36.90",
    "cardPrice": "--.--",
    "quantity": 0
  },
  {
    "id": "24001",
    "name": "Консерви 185 г Своя Лінія Тунець подрiбнений у власному соку з/б",
    "category": "М'ясні та рибні консерви",
    "imageUrl": "https://src.zakaz.atbmarket.com/cache/photos/30115/catalog_list_30115.jpg",
    "oldPrice": "51.90",
    "newPrice": "38.50",
    "cardPrice": "--.--",
    "quantity": 0
  },
  {
    "id": "23999",
    "name": "Консерви 185 г Своя Лінія Тунець подрiбнений в олії з/б",
    "category": "М'ясні та рибні консерви",
    "imageUrl": "https://src.zakaz.atbmarket.com/cache/photos/30113/catalog_list_30113.jpg",
    "oldPrice": "51.90",
    "newPrice": "38.50",
    "cardPrice": "--.--",
    "quantity": 0
  },
  {
    "id": "42627",
    "name": "Вареники 400 г День у День з сиром кисломолочним солодкі заморожені п/ет",
    "category": "Вареники, Пельмені, Млинці",
    "imageUrl": "https://src.zakaz.atbmarket.com/cache/photos/95137/catalog_list_95137.jpg",
    "oldPrice": "54.90",
    "newPrice": "39.90",
    "cardPrice": "--.--",
    "quantity": 0
  },
  {
    "id": "2287",
    "name": "Крем для гоління 65 мл Arko Cool",
    "category": "Засоби для гоління",
    "imageUrl": "https://src.zakaz.atbmarket.com/cache/photos/1861/catalog_list_1861.jpg",
    "oldPrice": "64.90",
    "newPrice": "40.50",
    "cardPrice": "--.--",
    "quantity": 0
  },
  {
    "id": "30567",
    "name": "Чай (24 ф/п х 1,5 г) Lovare зелений Citrus mellisa з ярликом к/уп",
    "category": "Чай",
    "imageUrl": "https://src.zakaz.atbmarket.com/cache/photos/55197/catalog_list_55197.jpg",
    "oldPrice": "68.60",
    "newPrice": "40.90",
    "cardPrice": "--.--",
    "quantity": 0
  },
  {
    "id": "25439",
    "name": "Чай (24 ф/п *2г) Lovare Champagne Splashes бленд чорного та зеленого з ягодами та аром. суниці к/уп",
    "category": "Чай",
    "imageUrl": "https://src.zakaz.atbmarket.com/cache/photos/33533/catalog_list_33533.jpg",
    "oldPrice": "68.60",
    "newPrice": "40.90",
    "cardPrice": "--.--",
    "quantity": 0
  },
  {
    "id": "4616",
    "name": "Олія 0,5л Своя лінія соняшникова рафінована",
    "category": "Олія та Оцет",
    "imageUrl": "https://src.zakaz.atbmarket.com/cache/photos/48117/catalog_list_48117.jpg",
    "oldPrice": "45.87",
    "newPrice": "41.70",
    "cardPrice": "--.--",
    "quantity": 0
  },
  {
    "id": "43357",
    "name": "Чай 70 г Своя Лінія Tropiccini суміш чорного та зеленого чаю з дод. екзотичних фруктів аром., м/уп",
    "category": "Чай",
    "imageUrl": "https://src.zakaz.atbmarket.com/cache/photos/98177/catalog_list_98177.jpg",
    "oldPrice": "59.90",
    "newPrice": "41.90",
    "cardPrice": "--.--",
    "quantity": 0
  },
  {
    "id": "43359",
    "name": "Чай 50 г Своя Лінія Alpine Traditions трав’яний з додаванням суміші плодів та ягід, м/уп",
    "category": "Чай",
    "imageUrl": "https://src.zakaz.atbmarket.com/cache/photos/98179/catalog_list_98179.jpg",
    "oldPrice": "59.90",
    "newPrice": "41.90",
    "cardPrice": "--.--",
    "quantity": 0
  },
  {
    "id": "831",
    "name": "Шоколад 90г Millennium Пористий Білий",
    "category": "Шоколад",
    "imageUrl": "https://src.zakaz.atbmarket.com/cache/photos/581/catalog_list_581.jpg",
    "oldPrice": "64.90",
    "newPrice": "42.90",
    "cardPrice": "--.--",
    "quantity": 0
  },
  {
    "id": "813",
    "name": "Шоколад 90г Millennium Пористий Молочний",
    "category": "Шоколад",
    "imageUrl": "https://src.zakaz.atbmarket.com/cache/photos/49807/catalog_list_49807.jpg",
    "oldPrice": "64.90",
    "newPrice": "42.90",
    "cardPrice": "--.--",
    "quantity": 0
  },
  {
    "id": "9413",
    "name": "Чай (25 ф/п х 2 г) Lovare чорний асорті 5 смаків м/уп з ярликом к/уп",
    "category": "Чай",
    "imageUrl": "https://src.zakaz.atbmarket.com/cache/photos/69809/catalog_list_69809.jpg",
    "oldPrice": "72.70",
    "newPrice": "43.20",
    "cardPrice": "--.--",
    "quantity": 0
  },
  {
    "id": "1812",
    "name": "Пиво 1,25л Своя Лінія Пивоварня №1 Міцне світле фільтроване",
    "category": "Пиво",
    "imageUrl": "https://src.zakaz.atbmarket.com/cache/photos/1772/catalog_list_1772.jpg",
    "oldPrice": "54.90",
    "newPrice": "43.50",
    "cardPrice": "--.--",
    "quantity": 0
  },
  {
    "id": "6801",
    "name": "Пресерви 180г Своя лінія Оселедець філе-шматочки в олії",
    "category": "Пресерви",
    "imageUrl": "https://src.zakaz.atbmarket.com/cache/photos/34139/catalog_list_34139.jpg",
    "oldPrice": "59.90",
    "newPrice": "44.90",
    "cardPrice": "--.--",
    "quantity": 0
  },
  {
    "id": "28649",
    "name": "Рідке мило 300мл Duru морські мінерали та олія авакадо п/флакон",
    "category": "Мило",
    "imageUrl": "https://src.zakaz.atbmarket.com/cache/photos/48395/catalog_list_48395.jpg",
    "oldPrice": "72.50",
    "newPrice": "44.90",
    "cardPrice": "--.--",
    "quantity": 0
  },
  {
    "id": "41619",
    "name": "Напій соковий 1,5 л Розумний вибір Виноград-гранат ПЕТ",
    "category": "Соки, нектари",
    "imageUrl": "https://src.zakaz.atbmarket.com/cache/photos/91591/catalog_list_91591.jpg",
    "oldPrice": "65.90",
    "newPrice": "45.90",
    "cardPrice": "--.--",
    "quantity": 0
  },
  {
    "id": "41621",
    "name": "Напій соковий 1,5 л Розумний вибір Яблуко-вишня ПЕТ",
    "category": "Соки, нектари",
    "imageUrl": "https://src.zakaz.atbmarket.com/cache/photos/91593/catalog_list_91593.jpg",
    "oldPrice": "65.90",
    "newPrice": "45.90",
    "cardPrice": "--.--",
    "quantity": 0
  },
  {
    "id": "41623",
    "name": "Напій соковмісний 1,5 л Розумнирй вибір смак Ананасу ПЕТ",
    "category": "Соки, нектари",
    "imageUrl": "https://src.zakaz.atbmarket.com/cache/photos/91595/catalog_list_91595.jpg",
    "oldPrice": "65.90",
    "newPrice": "45.90",
    "cardPrice": "--.--",
    "quantity": 0
  },
  {
    "id": "33101",
    "name": "Пиво 0,9 л GARAGE Seth & Riley's taste mandarin спеціальне пастеризоване ПЕТ",
    "category": "Пиво",
    "imageUrl": "https://src.zakaz.atbmarket.com/cache/photos/95893/catalog_list_95893.jpg",
    "oldPrice": "68.90",
    "newPrice": "46.00",
    "cardPrice": "--.--",
    "quantity": 0
  },
  {
    "id": "31509",
    "name": "Чипси 110 г Lay's Baked картопляні запечені зі смаком йогурту з травами м/уп",
    "category": "Чипси",
    "imageUrl": "https://src.zakaz.atbmarket.com/cache/photos/57327/catalog_list_57327.png",
    "oldPrice": "75.00",
    "newPrice": "48.70",
    "cardPrice": "--.--",
    "quantity": 0
  },
  {
    "id": "31511",
    "name": "Чипси 110 г Lay's Baked картопляні запечені зі смаком лисичок у сметані м/уп",
    "category": "Чипси",
    "imageUrl": "https://src.zakaz.atbmarket.com/cache/photos/57325/catalog_list_57325.png",
    "oldPrice": "75.00",
    "newPrice": "48.70",
    "cardPrice": "--.--",
    "quantity": 0
  },
  {
    "id": "1813",
    "name": "Консерви 325г Своя Лінія Курка з булгуром",
    "category": "М'ясні та рибні консерви",
    "imageUrl": "https://src.zakaz.atbmarket.com/cache/photos/76701/catalog_list_76701.png",
    "oldPrice": "66.90",
    "newPrice": "48.90",
    "cardPrice": "--.--",
    "quantity": 0
  },
  {
    "id": "38003",
    "name": "Засіб миючий для посуду 1 л День у День алое вера+гліцерин/цирус+зелений чай з дозатором п/флакон",
    "category": "Засоби для миття посуду",
    "imageUrl": "https://src.zakaz.atbmarket.com/cache/photos/80523/catalog_list_80523.jpg",
    "oldPrice": "72.70",
    "newPrice": "50.50",
    "cardPrice": "--.--",
    "quantity": 0
  },
  {
    "id": "8040",
    "name": "Суміш овочева 400г Своя Лінія для смаження WOK швидкозаморожена",
    "category": "Овочі та фрукти свіжозаморожені",
    "imageUrl": "https://src.zakaz.atbmarket.com/cache/photos/7233/catalog_list_7233.jpg",
    "oldPrice": "68.90",
    "newPrice": "51.50",
    "cardPrice": "--.--",
    "quantity": 0
  },
  {
    "id": "11989",
    "name": "Прокладки 16 шт Bella Perfecta Ultra Blue",
    "category": "Гігієнічні прокладки/тампони",
    "imageUrl": "https://src.zakaz.atbmarket.com/cache/photos/12540/catalog_list_12540.jpg",
    "oldPrice": "80.90",
    "newPrice": "51.90",
    "cardPrice": "--.--",
    "quantity": 0
  },
  {
    "id": "41617",
    "name": "Нeктap 1,5 л Розумний вибір Тoмaтний ПЕТ",
    "category": "Соки, нектари",
    "imageUrl": "https://src.zakaz.atbmarket.com/cache/photos/91589/catalog_list_91589.jpg",
    "oldPrice": "74.90",
    "newPrice": "51.90",
    "cardPrice": "--.--",
    "quantity": 0
  },
  {
    "id": "14773",
    "name": "Консерви 325 г Своя лінія філе індички з червоною квасолею",
    "category": "М'ясні та рибні консерви",
    "imageUrl": "https://src.zakaz.atbmarket.com/cache/photos/18021/catalog_list_18021.jpg",
    "oldPrice": "70.30",
    "newPrice": "51.90",
    "cardPrice": "--.--",
    "quantity": 0
  },
  {
    "id": "31517",
    "name": "Готовий Снідaнок 200 г Nesquik Mix м/yп",
    "category": "Сухі сніданки",
    "imageUrl": "https://src.zakaz.atbmarket.com/cache/photos/99279/catalog_list_99279.jpg",
    "oldPrice": "86.70",
    "newPrice": "53.60",
    "cardPrice": "--.--",
    "quantity": 0
  },
  {
    "id": "4228",
    "name": "Пиво 2,35л Оболонь Світле",
    "category": "Пиво",
    "imageUrl": "https://src.zakaz.atbmarket.com/cache/photos/72397/catalog_list_72397.jpg",
    "oldPrice": "95.00",
    "newPrice": "53.90",
    "cardPrice": "--.--",
    "quantity": 0
  },
  {
    "id": "28129",
    "name": "Сир напівтвердий 135г Serenada Салямі 45% пластини газ/упак",
    "category": "Сири тверді",
    "imageUrl": "https://src.zakaz.atbmarket.com/cache/photos/90355/catalog_list_90355.jpg",
    "oldPrice": "76.90",
    "newPrice": "56.90",
    "cardPrice": "--.--",
    "quantity": 0
  },
  {
    "id": "25469",
    "name": "Чай 80 г Lovare Champagne Splashes бленд чорного та зеленого з шматочками ягід та аром суниці к/уп",
    "category": "Чай",
    "imageUrl": "https://src.zakaz.atbmarket.com/cache/photos/33565/catalog_list_33565.jpg",
    "oldPrice": "95.60",
    "newPrice": "56.90",
    "cardPrice": "--.--",
    "quantity": 0
  },
  {
    "id": "7973",
    "name": "Пельмені 0,6 кг Левада Панські з яловичиною та свининою",
    "category": "Вареники, Пельмені, Млинці",
    "imageUrl": "https://src.zakaz.atbmarket.com/cache/photos/55887/catalog_list_55887.jpg",
    "oldPrice": "99.50",
    "newPrice": "57.50",
    "cardPrice": "--.--",
    "quantity": 0
  },
  {
    "id": "8002",
    "name": "Тісто 0,9 кг Своя лінія Листкове",
    "category": "Тісто, Випічка, Піца",
    "imageUrl": "https://src.zakaz.atbmarket.com/cache/photos/54587/catalog_list_54587.png",
    "oldPrice": "84.90",
    "newPrice": "58.90",
    "cardPrice": "--.--",
    "quantity": 0
  },
  {
    "id": "33537",
    "name": "Пиво 1,8 л Повна Діжка М'яке ПЕТ",
    "category": "Пиво",
    "imageUrl": "https://src.zakaz.atbmarket.com/cache/photos/66391/catalog_list_66391.jpg",
    "oldPrice": "90.50",
    "newPrice": "60.00",
    "cardPrice": "--.--",
    "quantity": 0
  },
  {
    "id": "1119",
    "name": "Оливки чорні 400г De Luxe Foods&Goods Selected",
    "category": "Овочева та фруктова консервація",
    "imageUrl": "https://src.zakaz.atbmarket.com/cache/photos/35163/catalog_list_35163.jpg",
    "oldPrice": "81.50",
    "newPrice": "61.10",
    "cardPrice": "--.--",
    "quantity": 0
  },
  {
    "id": "3528",
    "name": "Оливки чорні 400г De Luxe Foods&Goods Selected",
    "category": "Овочева та фруктова консервація",
    "imageUrl": "https://src.zakaz.atbmarket.com/cache/photos/35165/catalog_list_35165.jpg",
    "oldPrice": "81.50",
    "newPrice": "61.10",
    "cardPrice": "--.--",
    "quantity": 0
  },
  {
    "id": "1816",
    "name": "Консерви 325г Своя лінія Курица у власному соку безкісткове",
    "category": "М'ясні та рибні консерви",
    "imageUrl": "https://src.zakaz.atbmarket.com/cache/photos/76703/catalog_list_76703.png",
    "oldPrice": "83.90",
    "newPrice": "61.90",
    "cardPrice": "--.--",
    "quantity": 0
  },
  {
    "id": "9614",
    "name": "Сир твердий 100г Dziugas 40% тертий",
    "category": "Сири тверді",
    "imageUrl": "https://src.zakaz.atbmarket.com/cache/photos/9474/catalog_list_9474.jpg",
    "oldPrice": "83.90",
    "newPrice": "62.90",
    "cardPrice": "--.--",
    "quantity": 0
  },
  {
    "id": "2970",
    "name": "Сиp напiвтвepдий 150 г SERENADA Radamer пластини 45%",
    "category": "Сири тверді",
    "imageUrl": "https://src.zakaz.atbmarket.com/cache/photos/2142/catalog_list_2142.jpg",
    "oldPrice": "86.90",
    "newPrice": "63.90",
    "cardPrice": "--.--",
    "quantity": 0
  },
  {
    "id": "6132",
    "name": "Консерви 240г Своя лінія Шпроти в олії",
    "category": "М'ясні та рибні консерви",
    "imageUrl": "https://src.zakaz.atbmarket.com/cache/photos/35171/catalog_list_35171.jpg",
    "oldPrice": "89.30",
    "newPrice": "66.50",
    "cardPrice": "--.--",
    "quantity": 0
  },
  {
    "id": "3733",
    "name": "Піна для гоління 200+100 мл Arko Men Sensitive (промо)",
    "category": "Засоби для гоління",
    "imageUrl": "https://src.zakaz.atbmarket.com/cache/photos/95863/catalog_list_95863.jpg",
    "oldPrice": "106.90",
    "newPrice": "66.90",
    "cardPrice": "--.--",
    "quantity": 0
  },
  {
    "id": "5059",
    "name": "Піна для гоління 200+100 мл Arko Men Cool",
    "category": "Засоби для гоління",
    "imageUrl": "https://src.zakaz.atbmarket.com/cache/photos/95865/catalog_list_95865.jpg",
    "oldPrice": "106.90",
    "newPrice": "66.90",
    "cardPrice": "--.--",
    "quantity": 0
  },
  {
    "id": "37667",
    "name": "Вино 0,75 л FRATELLI FRAGOLINO BIANCO біле напівсолодке плодове столове 9-12% об ск/пл Україна",
    "category": "Вино",
    "imageUrl": "https://src.zakaz.atbmarket.com/cache/photos/79761/catalog_list_79761.jpg",
    "oldPrice": "116.40",
    "newPrice": "67.50",
    "cardPrice": "--.--",
    "quantity": 0
  },
  {
    "id": "37671",
    "name": "Вино 0,75 л FRATELLI FRAGOLINO ROSSO червоне напівсолодке плодове столове 9-12% об ск/пл Україна",
    "category": "Вино",
    "imageUrl": "https://src.zakaz.atbmarket.com/cache/photos/79765/catalog_list_79765.jpg",
    "oldPrice": "116.40",
    "newPrice": "67.50",
    "cardPrice": "--.--",
    "quantity": 0
  },
  {
    "id": "37669",
    "name": "Вино 0,75 л FRATELLI FRAGOLINO ROSATO рожеве напівсолодке плодове столове 9-12% об ск/пл Україна",
    "category": "Вино",
    "imageUrl": "https://src.zakaz.atbmarket.com/cache/photos/79763/catalog_list_79763.jpg",
    "oldPrice": "116.40",
    "newPrice": "67.50",
    "cardPrice": "--.--",
    "quantity": 0
  },
  {
    "id": "1750",
    "name": "Олія 0,9л Своя лінія соняшникова нерафінована",
    "category": "Олія та Оцет",
    "imageUrl": "https://src.zakaz.atbmarket.com/cache/photos/1183/catalog_list_1183.jpg",
    "oldPrice": "75.90",
    "newPrice": "67.60",
    "cardPrice": "--.--",
    "quantity": 0
  },
  {
    "id": "36665",
    "name": "Оливки зелені 400 г De Luxe Foods&Goods Selected б/к з/б",
    "category": "Овочева та фруктова консервація",
    "imageUrl": "https://src.zakaz.atbmarket.com/cache/photos/87249/catalog_list_87249.jpg",
    "oldPrice": "91.50",
    "newPrice": "68.50",
    "cardPrice": "--.--",
    "quantity": 0
  },
  {
    "id": "1700",
    "name": "Олія 0,9л Своя лінія соняшникова рафінована",
    "category": "Олія та Оцет",
    "imageUrl": "https://src.zakaz.atbmarket.com/cache/photos/1147/catalog_list_1147.jpg",
    "oldPrice": "75.90",
    "newPrice": "68.90",
    "cardPrice": "--.--",
    "quantity": 0
  },
  {
    "id": "1656",
    "name": "Пресерви 300г Своя лінія Оселедець філе-шматочки в олії",
    "category": "Пресерви",
    "imageUrl": "https://src.zakaz.atbmarket.com/cache/photos/54349/catalog_list_54349.png",
    "oldPrice": "92.90",
    "newPrice": "69.50",
    "cardPrice": "--.--",
    "quantity": 0
  },
  {
    "id": "9613",
    "name": "Сир твердий 100 г Dziugas 40% 12 міс. подрібнений",
    "category": "Сири тверді",
    "imageUrl": "https://src.zakaz.atbmarket.com/cache/photos/9473/catalog_list_9473.jpg",
    "oldPrice": "93.90",
    "newPrice": "69.90",
    "cardPrice": "--.--",
    "quantity": 0
  },
  {
    "id": "2076",
    "name": "Чай 180г Alokozay чорний байховий листовий FBOP",
    "category": "Чай",
    "imageUrl": "https://src.zakaz.atbmarket.com/cache/photos/1425/catalog_list_1425.jpg",
    "oldPrice": "110.40",
    "newPrice": "71.70",
    "cardPrice": "--.--",
    "quantity": 0
  },
  {
    "id": "4901",
    "name": "Гель для душу 250 мл Axe в асортименті (Dark Temptation/Apollo)",
    "category": "Гелі для душу",
    "imageUrl": "https://src.zakaz.atbmarket.com/cache/photos/95099/catalog_list_95099.jpg",
    "oldPrice": "119.90",
    "newPrice": "71.90",
    "cardPrice": "--.--",
    "quantity": 0
  },
  {
    "id": "16319",
    "name": "Мило туалетне 400 г Duru 1+1 Морські Мінерали + зволожуючий крем 5х80г",
    "category": "Мило",
    "imageUrl": "https://src.zakaz.atbmarket.com/cache/photos/37837/catalog_list_37837.jpg",
    "oldPrice": "118.40",
    "newPrice": "72.90",
    "cardPrice": "--.--",
    "quantity": 0
  },
  {
    "id": "16321",
    "name": "Милo туалетне 400 г Duru 1+1 Зелений чай + зволожуючий крем 5х80г",
    "category": "Мило",
    "imageUrl": "https://src.zakaz.atbmarket.com/cache/photos/37839/catalog_list_37839.jpg",
    "oldPrice": "118.40",
    "newPrice": "72.90",
    "cardPrice": "--.--",
    "quantity": 0
  },
  {
    "id": "30481",
    "name": "Пресерви 200г Своя Лінія Морський коктейль з морепродуктів в олії терморформа",
    "category": "Пресерви",
    "imageUrl": "https://src.zakaz.atbmarket.com/cache/photos/54729/catalog_list_54729.jpg",
    "oldPrice": "98.90",
    "newPrice": "73.90",
    "cardPrice": "--.--",
    "quantity": 0
  },
  {
    "id": "2280",
    "name": "Виноград Кишмиш",
    "category": "Фрукти, ягоди",
    "imageUrl": "https://src.zakaz.atbmarket.com/cache/photos/1857/catalog_list_1857.jpg",
    "oldPrice": "94.95",
    "newPrice": "75.95",
    "cardPrice": "--.--",
    "quantity": 0
  },
  {
    "id": "2030",
    "name": "Сир напівтвердий 200г SERENADA Radamer 45%",
    "category": "Сири тверді",
    "imageUrl": "https://src.zakaz.atbmarket.com/cache/photos/1381/catalog_list_1381.jpg",
    "oldPrice": "105.90",
    "newPrice": "77.90",
    "cardPrice": "--.--",
    "quantity": 0
  },
  {
    "id": "30993",
    "name": "Сир напівтвердий 200 г SERENADA Gouda 45% фас флоу-пак",
    "category": "Сири тверді",
    "imageUrl": "https://src.zakaz.atbmarket.com/cache/photos/55977/catalog_list_55977.jpg",
    "oldPrice": "105.90",
    "newPrice": "77.90",
    "cardPrice": "--.--",
    "quantity": 0
  },
  {
    "id": "42299",
    "name": "Дезодорант 150мл AXE Leather & Cookies / Epic Fresh аерозоль",
    "category": "Дезодоранти",
    "imageUrl": "https://src.zakaz.atbmarket.com/cache/photos/98123/catalog_list_98123.jpg",
    "oldPrice": "130.50",
    "newPrice": "77.90",
    "cardPrice": "--.--",
    "quantity": 0
  },
  {
    "id": "4540",
    "name": "Дезoдoрант 150 мл Axe (Apollo/Black) чoлoвічий",
    "category": "Дезодоранти",
    "imageUrl": "https://src.zakaz.atbmarket.com/cache/photos/86641/catalog_list_86641.jpg",
    "oldPrice": "130.50",
    "newPrice": "77.90",
    "cardPrice": "--.--",
    "quantity": 0
  },
  {
    "id": "2035",
    "name": "Ковбаса 420 г М'ясна лавка/Своя лінія Губернська н/к",
    "category": "Ковбаса",
    "imageUrl": "https://src.zakaz.atbmarket.com/cache/photos/87453/catalog_list_87453.jpg",
    "oldPrice": "137.00",
    "newPrice": "81.90",
    "cardPrice": "--.--",
    "quantity": 0
  },
  {
    "id": "38225",
    "name": "М'ясо мідій 350 г Своя Лінія варено-морожене в глазурі с/м вак/упак",
    "category": "Морепродукти",
    "imageUrl": "https://src.zakaz.atbmarket.com/cache/photos/81615/catalog_list_81615.jpg",
    "oldPrice": "119.90",
    "newPrice": "83.90",
    "cardPrice": "--.--",
    "quantity": 0
  },
  {
    "id": "4465",
    "name": "Прокладки урологічні 15 шт Seni Lady extra",
    "category": "Гігієнічні прокладки/тампони",
    "imageUrl": "https://src.zakaz.atbmarket.com/cache/photos/4009/catalog_list_4009.jpg",
    "oldPrice": "133.40",
    "newPrice": "85.90",
    "cardPrice": "--.--",
    "quantity": 0
  },
  {
    "id": "32227",
    "name": "Мийний засіб. Гель для прання 1,5л Fresini універсальний/для кольорових тканин п/флакон",
    "category": "Пральні порошки та засоби для прання",
    "imageUrl": "https://src.zakaz.atbmarket.com/cache/photos/71251/catalog_list_71251.jpg",
    "oldPrice": "134.90",
    "newPrice": "89.90",
    "cardPrice": "--.--",
    "quantity": 0
  },
  {
    "id": "13133",
    "name": "Піца 320г Passionata прошуто швидкозаморожена",
    "category": "Тісто, Випічка, Піца",
    "imageUrl": "https://src.zakaz.atbmarket.com/cache/photos/14480/catalog_list_14480.jpg",
    "oldPrice": "134.90",
    "newPrice": "93.90",
    "cardPrice": "--.--",
    "quantity": 0
  },
  {
    "id": "42163",
    "name": "Дезодорант 200 мл Axe Black/Dark Temptation аерозоль",
    "category": "Дезодоранти",
    "imageUrl": "https://src.zakaz.atbmarket.com/cache/photos/93669/catalog_list_93669.jpg",
    "oldPrice": "156.70",
    "newPrice": "93.90",
    "cardPrice": "--.--",
    "quantity": 0
  },
  {
    "id": "25429",
    "name": "Гель для гоління 200 мл Arko Cool/with Hemp seed oil",
    "category": "Засоби для гоління",
    "imageUrl": "https://src.zakaz.atbmarket.com/cache/photos/33515/catalog_list_33515.jpg",
    "oldPrice": "156.80",
    "newPrice": "97.90",
    "cardPrice": "--.--",
    "quantity": 0
  },
  {
    "id": "3242",
    "name": "Цукерки 154г Рошен Assortment Classic чорний шоколад",
    "category": "Цукерки",
    "imageUrl": "https://src.zakaz.atbmarket.com/cache/photos/29675/catalog_list_29675.jpg",
    "oldPrice": "178.90",
    "newPrice": "97.90",
    "cardPrice": "--.--",
    "quantity": 0
  },
  {
    "id": "3243",
    "name": "Цукерки 145г Рошен Assortment  Elegant молочний шоколад",
    "category": "Цукерки",
    "imageUrl": "https://src.zakaz.atbmarket.com/cache/photos/29677/catalog_list_29677.jpg",
    "oldPrice": "178.90",
    "newPrice": "97.90",
    "cardPrice": "--.--",
    "quantity": 0
  },
  {
    "id": "35159",
    "name": "Гель для гоління 240мл Arko Men Sensitive аерозоль",
    "category": "Засоби для гоління",
    "imageUrl": "https://src.zakaz.atbmarket.com/cache/photos/72645/catalog_list_72645.jpg",
    "oldPrice": "160.60",
    "newPrice": "99.90",
    "cardPrice": "--.--",
    "quantity": 0
  },
  {
    "id": "27105",
    "name": "Горілка 0,5 л Козацька Рада Особлива 40% об ск/бут",
    "category": "Горілка",
    "imageUrl": "https://src.zakaz.atbmarket.com/cache/photos/69137/catalog_list_69137.png",
    "oldPrice": "140.80",
    "newPrice": "99.90",
    "cardPrice": "--.--",
    "quantity": 0
  },
  {
    "id": "8067",
    "name": "Пельмені 0,8 кг Левада Фірмові з яловичиною",
    "category": "Вареники, Пельмені, Млинці",
    "imageUrl": "https://src.zakaz.atbmarket.com/cache/photos/7259/catalog_list_7259.jpg",
    "oldPrice": "178.50",
    "newPrice": "102.90",
    "cardPrice": "--.--",
    "quantity": 0
  },
  {
    "id": "24355",
    "name": "Ковбаски 0,5 кг для гриля #ЦЕМ'ЯСО Часникові свинячі охолоджені газ/упак",
    "category": "М'ясні напівфабрикати",
    "imageUrl": "https://src.zakaz.atbmarket.com/cache/photos/80347/catalog_list_80347.jpg",
    "oldPrice": "128.00",
    "newPrice": "104.90",
    "cardPrice": "--.--",
    "quantity": 0
  },
  {
    "id": "3614",
    "name": "Вермут 1л FRATELLI Limoncello лікерний білий 12,5%",
    "category": "Вермут",
    "imageUrl": "https://src.zakaz.atbmarket.com/cache/photos/25231/catalog_list_25231.jpg",
    "oldPrice": "184.90",
    "newPrice": "105.00",
    "cardPrice": "--.--",
    "quantity": 0
  },
  {
    "id": "43023",
    "name": "Вермут 1 л FRATELLI Moscato Bianco лікерний білий 12,5% об ск/бут",
    "category": "Вермут",
    "imageUrl": "https://src.zakaz.atbmarket.com/cache/photos/96293/catalog_list_96293.jpg",
    "oldPrice": "184.90",
    "newPrice": "105.00",
    "cardPrice": "--.--",
    "quantity": 0
  },
  {
    "id": "29599",
    "name": "Пивo 4х0,48л Staropramen НАБІР з/б",
    "category": "Пиво",
    "imageUrl": "https://src.zakaz.atbmarket.com/cache/photos/52655/catalog_list_52655.jpg",
    "oldPrice": "163.50",
    "newPrice": "107.50",
    "cardPrice": "--.--",
    "quantity": 0
  },
  {
    "id": "7963",
    "name": "Пельмені 0,9 кг Левада З яловичиною та свининою",
    "category": "Вареники, Пельмені, Млинці",
    "imageUrl": "https://src.zakaz.atbmarket.com/cache/photos/55883/catalog_list_55883.jpg",
    "oldPrice": "194.90",
    "newPrice": "112.90",
    "cardPrice": "--.--",
    "quantity": 0
  },
  {
    "id": "37199",
    "name": "Цукерки 240 г Своя Лінія Пташине молоко к/уп",
    "category": "Цукерки",
    "imageUrl": "https://src.zakaz.atbmarket.com/cache/photos/79673/catalog_list_79673.jpg",
    "oldPrice": "163.90",
    "newPrice": "112.90",
    "cardPrice": "--.--",
    "quantity": 0
  },
  {
    "id": "7967",
    "name": "Морозиво 0,5 кг Три Ведмеді Фісташка",
    "category": "Морозиво",
    "imageUrl": "https://src.zakaz.atbmarket.com/cache/photos/68687/catalog_list_68687.jpg",
    "oldPrice": "207.90",
    "newPrice": "113.90",
    "cardPrice": "--.--",
    "quantity": 0
  },
  {
    "id": "43857",
    "name": "Кава розчинна 100 г Своя Лінія Coffee Gold Original сублімована м/уп",
    "category": "Кава, какао",
    "imageUrl": "https://src.zakaz.atbmarket.com/cache/photos/99785/catalog_list_99785.jpg",
    "oldPrice": "179.90",
    "newPrice": "116.90",
    "cardPrice": "--.--",
    "quantity": 0
  },
  {
    "id": "2971",
    "name": "Ковбаса 0,5 кг Добров Лікарська вар",
    "category": "Ковбаса",
    "imageUrl": "https://src.zakaz.atbmarket.com/cache/photos/2143/catalog_list_2143.png",
    "oldPrice": "186.60",
    "newPrice": "123.90",
    "cardPrice": "--.--",
    "quantity": 0
  },
  {
    "id": "9591",
    "name": "Сир твердий 180 г Dziugas 40%, Литва",
    "category": "Сири тверді",
    "imageUrl": "https://src.zakaz.atbmarket.com/cache/photos/9458/catalog_list_9458.jpg",
    "oldPrice": "168.90",
    "newPrice": "125.90",
    "cardPrice": "--.--",
    "quantity": 0
  },
  {
    "id": "43631",
    "name": "Дезодорант 200 мл Old Spice Wolfthron антиперспірант аерозоль",
    "category": "Дезодоранти",
    "imageUrl": "https://src.zakaz.atbmarket.com/cache/photos/98897/catalog_list_98897.jpg",
    "oldPrice": "191.20",
    "newPrice": "129.00",
    "cardPrice": "--.--",
    "quantity": 0
  },
  {
    "id": "43629",
    "name": "Дезодорант 200 мл Old Spice Whitewater антиперспірант аерозоль",
    "category": "Дезодоранти",
    "imageUrl": "https://src.zakaz.atbmarket.com/cache/photos/98895/catalog_list_98895.jpg",
    "oldPrice": "191.20",
    "newPrice": "129.00",
    "cardPrice": "--.--",
    "quantity": 0
  },
  {
    "id": "11873",
    "name": "Шампунь 400 мл Gliss Kur Oil Nutritive",
    "category": "Шампуні",
    "imageUrl": "https://src.zakaz.atbmarket.com/cache/photos/12412/catalog_list_12412.jpg",
    "oldPrice": "193.50",
    "newPrice": "129.90",
    "cardPrice": "--.--",
    "quantity": 0
  },
  {
    "id": "11987",
    "name": "Шампунь 400 мл Gliss Kur Ultimate Repair для дуже пошкодженого та сухого волосся",
    "category": "Шампуні",
    "imageUrl": "https://src.zakaz.atbmarket.com/cache/photos/30573/catalog_list_30573.png",
    "oldPrice": "193.50",
    "newPrice": "129.90",
    "cardPrice": "--.--",
    "quantity": 0
  },
  {
    "id": "3785",
    "name": "Вино 1,5л Коблево Шато Сен-Жермен  біле напівсолодке 9-12%, Україна",
    "category": "Вино",
    "imageUrl": "https://src.zakaz.atbmarket.com/cache/photos/27719/catalog_list_27719.jpg",
    "oldPrice": "194.60",
    "newPrice": "135.00",
    "cardPrice": "--.--",
    "quantity": 0
  },
  {
    "id": "12435",
    "name": "Вино 1,5 л Коблево Бордо Riesling біле сухе 9-12%, Україна",
    "category": "Вино",
    "imageUrl": "https://src.zakaz.atbmarket.com/cache/photos/27751/catalog_list_27751.jpg",
    "oldPrice": "194.60",
    "newPrice": "135.00",
    "cardPrice": "--.--",
    "quantity": 0
  },
  {
    "id": "27481",
    "name": "Гель для прання 4кг WASH&FREE універсальний жасмин та лаванда з марсельським милом п/флакон",
    "category": "Пральні порошки та засоби для прання",
    "imageUrl": "https://src.zakaz.atbmarket.com/cache/photos/60759/catalog_list_60759.jpg",
    "oldPrice": "226.60",
    "newPrice": "140.00",
    "cardPrice": "--.--",
    "quantity": 0
  },
  {
    "id": "606",
    "name": "Вино 0,75л Leonard Kreusch Riesling SS біле напівсолодке 9,5%, Німеччина",
    "category": "Вино",
    "imageUrl": "https://src.zakaz.atbmarket.com/cache/photos/98303/catalog_list_98303.png",
    "oldPrice": "189.90",
    "newPrice": "146.00",
    "cardPrice": "--.--",
    "quantity": 0
  },
  {
    "id": "13129",
    "name": "Корм 2,4 кг Friskies сухий для активних дорослих собак",
    "category": "Корм",
    "imageUrl": "https://src.zakaz.atbmarket.com/cache/photos/92487/catalog_list_92487.jpg",
    "oldPrice": "244.00",
    "newPrice": "159.90",
    "cardPrice": "--.--",
    "quantity": 0
  },
  {
    "id": "31229",
    "name": "Напій лікеро-горілчаний 0,7 л Retro Pina Colada 14% об ск/пл Бельгія",
    "category": "Лікери, настоянки, бальзами",
    "imageUrl": "https://src.zakaz.atbmarket.com/cache/photos/56635/catalog_list_56635.png",
    "oldPrice": "216.90",
    "newPrice": "160.00",
    "cardPrice": "--.--",
    "quantity": 0
  },
  {
    "id": "1553",
    "name": "Кoрм 0,8 кг PURINA ONE STERILCAT сухий для кастрованих котів/стерил.кішок з лососем та пшеницею",
    "category": "Корм",
    "imageUrl": "https://src.zakaz.atbmarket.com/cache/photos/92451/catalog_list_92451.jpg",
    "oldPrice": "251.50",
    "newPrice": "163.90",
    "cardPrice": "--.--",
    "quantity": 0
  },
  {
    "id": "1192",
    "name": "Цукерки 176г Рошен Київ Вечірній",
    "category": "Цукерки",
    "imageUrl": "https://src.zakaz.atbmarket.com/cache/photos/45405/catalog_list_45405.jpg",
    "oldPrice": "360.90",
    "newPrice": "175.90",
    "cardPrice": "--.--",
    "quantity": 0
  },
  {
    "id": "3880",
    "name": "Цукерки 194г Рошен Roshen Chocolateria шоколадні та пралінові",
    "category": "Цукерки",
    "imageUrl": "https://src.zakaz.atbmarket.com/cache/photos/3575/catalog_list_3575.jpg",
    "oldPrice": "360.90",
    "newPrice": "175.90",
    "cardPrice": "--.--",
    "quantity": 0
  },
  {
    "id": "29253",
    "name": "Цукерки Своя Лінія Cocos Paradise вагові",
    "category": "Цукерки",
    "imageUrl": "https://src.zakaz.atbmarket.com/cache/photos/51271/catalog_list_51271.jpg",
    "oldPrice": "241.90",
    "newPrice": "179.90",
    "cardPrice": "--.--",
    "quantity": 0
  },
  {
    "id": "993",
    "name": "Сардельки Своя лінія Австрійські",
    "category": "Сосиски, сардельки",
    "imageUrl": "https://src.zakaz.atbmarket.com/cache/photos/703/catalog_list_703.jpg",
    "oldPrice": "317.99",
    "newPrice": "189.89",
    "cardPrice": "--.--",
    "quantity": 0
  },
  {
    "id": "37621",
    "name": "Кава 250 г CARTE NOIRE ESPRESSO мелена м/уп",
    "category": "Кава, какао",
    "imageUrl": "https://src.zakaz.atbmarket.com/cache/photos/98153/catalog_list_98153.jpg",
    "oldPrice": "396.40",
    "newPrice": "197.90",
    "cardPrice": "--.--",
    "quantity": 0
  },
  {
    "id": "43347",
    "name": "Минтай День у День філе с/м н/ш п/ет",
    "category": "Риба",
    "imageUrl": "https://src.zakaz.atbmarket.com/cache/photos/98167/catalog_list_98167.jpg",
    "oldPrice": "255.89",
    "newPrice": "199.90",
    "cardPrice": "--.--",
    "quantity": 0
  },
  {
    "id": "43859",
    "name": "Кава розчинна 200 г Своя Лінія Coffee Gold Original сублімована м/уп",
    "category": "Кава, какао",
    "imageUrl": "https://src.zakaz.atbmarket.com/cache/photos/99787/catalog_list_99787.jpg",
    "oldPrice": "309.90",
    "newPrice": "199.90",
    "cardPrice": "--.--",
    "quantity": 0
  },
  {
    "id": "5201",
    "name": "Сьомга 210г Norven слабосолена філе-шматок на шкірі",
    "category": "Риба",
    "imageUrl": "https://src.zakaz.atbmarket.com/cache/photos/54353/catalog_list_54353.png",
    "oldPrice": "315.40",
    "newPrice": "215.90",
    "cardPrice": "--.--",
    "quantity": 0
  },
  {
    "id": "10822",
    "name": "Вино ігристе 0,75 л Borghesia Prosecco брют біле 11%, Італія",
    "category": "Ігристе вино",
    "imageUrl": "https://src.zakaz.atbmarket.com/cache/photos/98327/catalog_list_98327.png",
    "oldPrice": "319.90",
    "newPrice": "223.50",
    "cardPrice": "--.--",
    "quantity": 0
  },
  {
    "id": "4061",
    "name": "Олія 3л Своя лінія соняшникова рафінована",
    "category": "Олія та Оцет",
    "imageUrl": "https://src.zakaz.atbmarket.com/cache/photos/2669/catalog_list_2669.jpg",
    "oldPrice": "250.60",
    "newPrice": "227.50",
    "cardPrice": "--.--",
    "quantity": 0
  },
  {
    "id": "1927",
    "name": "Філе куряче Наша Ряба охолоджене упаковка",
    "category": "М'ясо охолоджене",
    "imageUrl": "https://src.zakaz.atbmarket.com/cache/photos/98927/catalog_list_98927.jpg",
    "oldPrice": "243.29",
    "newPrice": "229.89",
    "cardPrice": "--.--",
    "quantity": 0
  },
  {
    "id": "5124",
    "name": "Кава 140г Carte Noire розчинна сублімована",
    "category": "Кава, какао",
    "imageUrl": "https://src.zakaz.atbmarket.com/cache/photos/68121/catalog_list_68121.png",
    "oldPrice": "501.50",
    "newPrice": "249.90",
    "cardPrice": "--.--",
    "quantity": 0
  },
  {
    "id": "38011",
    "name": "Гель для душу + шампунь 1 л Old Spice 3-в-1 Whitewater п/флакон",
    "category": "Гелі для душу",
    "imageUrl": "https://src.zakaz.atbmarket.com/cache/photos/93547/catalog_list_93547.jpg",
    "oldPrice": "385.90",
    "newPrice": "259.00",
    "cardPrice": "--.--",
    "quantity": 0
  },
  {
    "id": "30019",
    "name": "Ковбaсa М'яснa лaвкa/Своя лінія Салямі Фірмова с/к вaк/yпaк",
    "category": "Ковбаса",
    "imageUrl": "https://src.zakaz.atbmarket.com/cache/photos/53675/catalog_list_53675.png",
    "oldPrice": "457.39",
    "newPrice": "292.69",
    "cardPrice": "--.--",
    "quantity": 0
  },
  {
    "id": "41445",
    "name": "Засіб миючий синтетичний 2,25 кг Ariel Aqua Puder Color м/уп",
    "category": "Пральні порошки та засоби для прання",
    "imageUrl": "https://src.zakaz.atbmarket.com/cache/photos/91417/catalog_list_91417.jpg",
    "oldPrice": "485.00",
    "newPrice": "295.00",
    "cardPrice": "--.--",
    "quantity": 0
  },
  {
    "id": "40369",
    "name": "Підгузники-трусики 30 шт Huggies Little Movers Pants (4) дитячі м/уп",
    "category": "Підгузки, пелюшки",
    "imageUrl": "https://src.zakaz.atbmarket.com/cache/photos/89007/catalog_list_89007.jpg",
    "oldPrice": "475.00",
    "newPrice": "337.00",
    "cardPrice": "--.--",
    "quantity": 0
  },
  {
    "id": "40367",
    "name": "Підгузники-трусики 28 шт Huggies Little Movers Pants (5) дитячі м/уп",
    "category": "Підгузки, пелюшки",
    "imageUrl": "https://src.zakaz.atbmarket.com/cache/photos/89005/catalog_list_89005.jpg",
    "oldPrice": "475.00",
    "newPrice": "337.00",
    "cardPrice": "--.--",
    "quantity": 0
  },
  {
    "id": "40365",
    "name": "Підгузники-трусики 26 шт Huggies Movers Pants Pants (6) дитячі м/уп",
    "category": "Підгузки, пелюшки",
    "imageUrl": "https://src.zakaz.atbmarket.com/cache/photos/89003/catalog_list_89003.jpg",
    "oldPrice": "475.00",
    "newPrice": "337.00",
    "cardPrice": "--.--",
    "quantity": 0
  },
  {
    "id": "3124",
    "name": "Напій 0,7л Captain Morgan Original Spiced Gold алкогольний на основі рому 35%",
    "category": "Інший алкоголь",
    "imageUrl": "https://src.zakaz.atbmarket.com/cache/photos/63263/catalog_list_63263.jpg",
    "oldPrice": "618.90",
    "newPrice": "399.00",
    "cardPrice": "--.--",
    "quantity": 0
  },
  {
    "id": "6666",
    "name": "Підгузники 40 шт Huggies Elite Soft extra care (3) 5-9 кг дитячі м/уп",
    "category": "Підгузки, пелюшки",
    "imageUrl": "https://src.zakaz.atbmarket.com/cache/photos/68705/catalog_list_68705.jpg",
    "oldPrice": "642.90",
    "newPrice": "456.00",
    "cardPrice": "--.--",
    "quantity": 0
  },
  {
    "id": "10817",
    "name": "Підгузники 33 шт Huggies Elite Soft (4) дитячі",
    "category": "Підгузки, пелюшки",
    "imageUrl": "https://src.zakaz.atbmarket.com/cache/photos/69541/catalog_list_69541.jpg",
    "oldPrice": "642.90",
    "newPrice": "456.00",
    "cardPrice": "--.--",
    "quantity": 0
  },
  {
    "id": "17491",
    "name": "Кава 1 кг De Luxe Foods&Goods Selected в зернах",
    "category": "Кава, какао",
    "imageUrl": "https://src.zakaz.atbmarket.com/cache/photos/27377/catalog_list_27377.jpg",
    "oldPrice": "920.90",
    "newPrice": "671.90",
    "cardPrice": "--.--",
    "quantity": 0
  }
]